Unpipelined/imem_tb.v
`include "MIPS_Single_Cycle.v"




module imem_tb;


    reg [5:0] address;
    wire [31:0] data;


    initial begin
        $dumpfile("imem_tb.vcd");
        $dumpvars;
        $display("starting imem test");
    end

    instruction_memory dut(data,address);

    initial begin
 
        for(integer i=0;i<1000;i++) begin
            address=i; #10;
        end
    end

endmodule

Unpipelined/MIPS_Single_Cycle.v
//on reset PC should begin at 0xBFC0 0000

module MIPS_Single_Cycle();

    initial begin

    end
endmodule


//32 bit flip flop with active high reset 
module Dflipflop(Q, clk, D, reset);

    input clk, reset; 
    input [31:0] D;
    output reg [31:0] Q;

    always @ (posedge clk)
        begin
            if(reset==1) Q<=0;

            Q<=D; //output new pc from alu on posedge clk 
        end
endmodule



//register file. Contains 32 internal registers. each 32 bits wide
//address 1 (A1) is read to RD1 asynchronously. Same is true for A2 and RD2.
//To write, input address is A3. Address to read is WD3. occurs on posedge clk
//write enable must also be active. 
module registerFile(RD1, RD2, A1, A2, A3, WD3, clk, WE3);
    
    output [31:0] RD1, RD2;  //outputs of the register file are each 32 bits since the regsiter is 32 bits wide
    input [4:0] A1,A2,A3;   //2^5=32 since 32 total addresses
    input [31:0] WD3; //the data to be written if WE3 is high 
    input clk, WE3; 

    reg [31:0] internal_mem [31:0]; //32 wires each 32 bits long

    
        always @ (posedge clk) 
            if (WE3==1) internal_mem[A3]<=WD3;
        
        assign RD1[0]=0;    //register 0 is always 0
        assign RD1=internal_mem[A1];
        assign RD2=internal_mem[A2];

endmodule


//in single cycle mips architecture, the program and variables are stored in
//two seperate registers. instruction memory stores the program, Data memory
//(TBD) stores variable information
module instruction_memory(RD, A);
    output [31:0] RD;    //output data is 32 bits wide because thats how long instructions are
    input [5:0] A;      //64 possible addresses

    reg [31:0] RAM [63:0]; //64 wires each 32 bits wide
    
    initial
        begin 
            $readmemh("memfile.dat",RAM); //read dissassembled MIPS code and load it into ram
    end

    assign RD = RAM[A]; //output onto bus. no need for clock because ram is asynchronous

endmodule




//more ram. This is where data is written during program exectuion. 
//writing is done on the clock, reading is done asynchronously
//input address is 32 bits, data width is 32 bits. 
module data_memory(RD,clk,A,WD,WE);
    //not using full memory capabilities
    //
    //
    //                                                                                                                      DOUBLE
    //                                                                                                                      CHECK
    //                                                                                                                      THIS
    //                                                                                                                      MODULE
    output [31:0] RD;
    input clk, WE;
    input [31:0] A,WD;


    reg [31:0] data [63:0];


    assign RD = data[A]; //address is always being read out

    always @ (posedge clk)
        if(WE==1) data[A] <=WD;
endmodule



module SignExtender(extend, extended);

    input [15:0] extend;
    output [31:0] extended;

    assign extended[31:0]= {{16{extend[15]}},extend[15:0]};

endmodule

module adder(Y, C_out, SrcA, SrcB);

    output [31:0] Y;
    output C_out;
    input [31:0] SrcA, SrcB;
    

    assign {C_out,Y}=SrcA+SrcB;


endmodule



//The input to the alu control logic depends on 2 things, the op code and the
//funct space (in R type instructions). For instance, an instruction with
//opcode 000000 is always going to have an AluOp of 10. 10 indicates that the
//ALUcontrol depends on the funct field of the instruction, (Or, Nor, Add all
//work differently). However, in I type instructions, there is no funct field,
//so the alu controll only depends on the opcode, and the logic for that is
//quite straight forward. 

//ALU decoder controls the operation that occurs in the alu
module AluDecoder(AluControl, AluOP, funct);

    output reg [2:0]AluControl;
    input [1:0] AluOP;
    input [5:0] funct;
    


    always @(*)
        if (AluOP==2'b0x) AluControl<=3'b010;
        else if (AluOP==2'bx1) AluControl <=3'b110;
        else if(AluOP==2'b1x) case(funct)
            6'b100000 : AluControl <= 3'b010;   //add
            6'b100010 : AluControl <= 3'b110;   //sub
            6'b100100 : AluControl <= 3'b000;   //and
            6'b100101 : AluControl <= 3'b001;   //or
            6'b101010 : AluControl <= 3'b011;   //slt
        default: AluControl <=3'bxxx;   //illegal opcode
        endcase
endmodule


module Or(Y, SrcA,SrcB);

    output [31:0] Y;
    input [31:0] SrcA, SrcB;


    assign Y=SrcA | SrcB;

endmodule

module And(Y, SrcA,SrcB);

    output [31:0] Y;
    input [31:0] SrcA, SrcB;


    assign Y=SrcA & SrcB;

endmodule
//subtract and add are done the same exact way. the only difference is that 
//subtract is compiled as the addition of a twos complement number to
//a posative 
module ALU(Zero, ALUResult, C_out, ALUControl, SrcA, SrcB);

    output reg Zero;
    output [31:0] ALUResult;
    output C_out;
    input [2:0] ALUControl;
    input [31:0] SrcA, SrcB;
    
    wire [31:0] SrcB_not; assign SrcB_not=~SrcB;
    wire [31:0] mux1_out;
    wire [31:0] N0,N1,N2,N3;


    mux_2_32b mux1(mux1_out,ALUControl[2], SrcB,SrcB_not);
 
    assign N0=mux1_out&SrcA;

    assign N1=mux1_out&SrcA;


    adder add1(N2,C_out,mux1_out,SrcA);
    assign N3={1'b0,N2[30:0]};

    mux_4_32b mux2(ALUResult,ALUControl[1:0],N0,N1,N2,N3);

    always @(*)
        if (ALUResult==0) Zero=1;
        else Zero=0;

endmodule








module shift_left_2(shifted_out,shift_in);

    input [31:0] shift_in;
    output [31:0] shifted_out;


    assign shifted_out=shift_in<<2;
endmodule


module mux_2_32b(out, sel, D0, D1);

    output [31:0] out;
    input sel;
    input [31:0] D0, D1;
    
    assign out=sel? D1:D0;

endmodule


module mux_4_32b(out, sel, D0, D1, D2, D3);

    output [31:0] out;
    input [1:0]sel;
    input [31:0] D0, D1, D2, D3;
    
    assign out=sel[1]? (sel[0]?D3:D2):(sel[0]? D1: D0);

endmodule




//The main decoder for the system. Seperate from ALU decoder. This can be
//viewed as the microcode of the system for each instruction. 
module mainDecoder(MemWrite, RegWrite, RegDst, ALUSrc, MemtoReg, Branch, ALUOp, Jump, Opcode);
    output MemWrite, RegWrite, RegDst, ALUSrc, MemtoReg, Branch, Jump;
    output [1:0] ALUOp;
    input [5:0] Opcode;

    reg [8:0] controls;

    assign {RegWrite,RegDst,ALUSrc,Branch,MemWrite,MemtoReg,ALUOp,Jump}=controls;
    always @(*)
        if(Opcode==6'b000000) assign controls=9'b110000100;
        else if(Opcode==6'b100011) assign controls=9'b101001000;           
        else if (Opcode==6'b101011) assign controls=9'b0x101x000;
        else if (Opcode==6'b000100) assign controls=9'b0x010x010;
        else if (Opcode==6'b001000) assign controls=9'b101000000;
        else if (Opcode==6'b000010) assign controls=9'b0xxx0xxx1;
        else assign controls=9'bxxxxxxxxx;
endmodule


module controller (ALUControl, PCSrc, MemtoReg,ALUSrc,RegDst,RegWrite, MemWrite, Opcode, Funct, Zero, Jump);

    
    output [2:0] ALUControl;
    output PCSrc, MemtoReg, ALUSrc, RegDst, RegWrite, MemWrite,Jump;

    input [5:0] Funct;
    input [5:0] Opcode;
    input Zero;
    
    wire Branch;
    wire [1:0] ALUOp;

    mainDecoder md1(MemWrite, RegWrite, RegDst, ALUSrc, MemtoReg, Branch, ALUOp, Jump, Opcode);

    AluDecoder aludec1(ALUControl, ALUOp,Funct);

    assign PCSrc=Branch & Zero; //source of pc.


endmodule



module datapath(ALUOut, WriteData, PC, Zero, Reset, Clk, ALUControl, PCSrc, MemtoReg, ALUSrc, RegDst, RegWrite, Jump, ReadData,Instr);

    output Zero; //zero flag if alu output is 0
    output [31:0] PC; //program counter output after selection (final PC for instruction retrieving)
    output [31:0] ALUOut, WriteData;
    
    input Reset, Clk, MemtoReg, PCSrc, ALUSrc, RegDst, RegWrite, Jump;
    input [2:0] ALUControl; 
    input [31:0] ReadData; //inputs datat to datapath
    input [31:0] Instr;

    wire [4:0] RegisterAddress; //address if writing to registers (A3)
    
    
    wire [31:0] PCNext, PCNextbr, PCPlus4, PCBranch; 
    //PCPLUS4 is the output of the ALU after adding 4
    //PCBranch is the PC value after a branch instruction (which uses relative addressing)
    //PCNextbr is the output of the mux after selecting between branching and just adding 4
    
    //PCNext is the value of the PC that is stored in the PC regitser

    wire [31:0] SignImm, SignImmSh;
    //a branch may be posative or negative. Since the PC is 32 bits and the
    //largest possible relative address is 16 bits, it must be extended to 32
    //bits with the correct sign in mind. 
    //SignImm is the unextended branch value (relative address) and SignImmSh
    //is the sign extended relative address inputted to the PC ALU

    wire [31:0] SrcA, SrcB; 
    //inputs to the main ALU

    wire [31:0] Result;
    //This is not the alu resut, it is the output of the mux that selects
    //between data memory outout and aluoutput. This is imporatnt as it
    //determines what is written to the register file
    

    Dflipflop PCRegister(PC,Clk, PCNext, Reset);
    //PCRegister


    adder pcadd1(PCPlus4,,32'b100,PC); //the adder for the Program counter iteration

    shift_left_2 immsh(SignImmSh,SignImm);
    //shiftng for branch operatioms (multiply by 4)

    adder pcadd2 (PCBranch,,SignImmSh,PCPlus4);
    //the adder for branch operations. number of bytes+PC
    
    mux_2_32b pcbrmux(PCNextbr,PCSrc, PCPlus4, PCBranch);
    //this mux determines if the pc should use the next address(PC+4) or the
    //branched PC (PCBranch) address based on contrrol logic from main dec

    mux_2_32b pcmux(PCNext, Jump,PCNextbr, {PCPlus4[31:28],Instr[25:0], 2'b00});



    


    //register file 
    

    registerFile rf(SrcA, WriteData,Instr[25:21],Instr[20:16],RegisterAddress,WriteData,Clk, RegWrite);

    mux_2_5b A3Mux(RegisterAddress,RegDst,Instr[20:16],Instr[25:21]);

    mux_2_32b WD3Mux(Result,MemtoReg,ALUOut, ReadData);

    SignExtender se(Instr[15:0],SignImm);
    //ALU
    mux_2_32b SRCBmux (SrcB, ALUSrc, WriteData, SignImm);
    
    ALU alu_main (Zero, ALUOut, , ALUControl,SrcA, SrcB);




endmodule

module mux_2_5b(out, sel, D0, D1); //for controlling A3

    output [4:0] out;
    input sel;
    input [4:0] D0, D1;
    
    assign out=sel? D1:D0;

endmodule


module MIPS (ALUOut,WriteData,WE, PC,Instr,ReadData,Reset,Clk);

    output  WE; //write enable
    output [31:0] ALUOut,WriteData;
    output [31:0] PC;
    input [31:0] Instr, ReadData;
    input Reset,Clk;

    wire MemToReg, Branch,ALUSrc, RegDst, RegWrite, Jump,PCSrc,Zero;
    wire [2:0] ALUControl;
    
    controller control(ALUControl,PCSrc,MemToReg,ALUSrc,RegDst,RegWrite,WE,Instr[31:26],Instr[5:0],Zero,Jump);


    datapath dp(ALUOut, WriteData, PC, Zero, Reset, Clk, ALUControl, PCSrc, MemToReg, ALUSrc, RegDst, RegWrite, Jump, ReadData,Instr);


endmodule


module top(Clk, Reset, WriteData,DataAdr,WE);

    input Clk, Reset;
    output [31:0] WriteData, DataAdr;
    output WE;


    wire [31:0] PC, Instr, ReadData;


    MIPS mips(DataAdr,WriteData,WE, PC,Instr,ReadData,Reset,Clk);


    instruction_memory imem(Instr,PC[7:2]);

    data_memory dmem(ReadData, Clk, DataAdr, WriteData, WE);

endmodule

Unpipelined/imem_tb.vcd
$date
	Wed Jun  1 19:32:52 2022
$end
$version
	Icarus Verilog
$end
$timescale
	1s
$end
$scope module And $end
$var wire 32 ! SrcA [31:0] $end
$var wire 32 " SrcB [31:0] $end
$var wire 32 # Y [31:0] $end
$upscope $end
$scope module MIPS_Single_Cycle $end
$upscope $end
$scope module Or $end
$var wire 32 $ SrcA [31:0] $end
$var wire 32 % SrcB [31:0] $end
$var wire 32 & Y [31:0] $end
$upscope $end
$scope module imem_tb $end
$var wire 32 ' data [31:0] $end
$var reg 6 ( address [5:0] $end
$scope module dut $end
$var wire 6 ) A [5:0] $end
$var wire 32 * RD [31:0] $end
$upscope $end
$scope begin $ivl_for_loop0 $end
$var integer 32 + i [31:0] $end
$upscope $end
$upscope $end
$scope module top $end
$var wire 1 , Clk $end
$var wire 1 - Reset $end
$var wire 32 . WriteData [31:0] $end
$var wire 1 / WE $end
$var wire 32 0 ReadData [31:0] $end
$var wire 32 1 PC [31:0] $end
$var wire 32 2 Instr [31:0] $end
$var wire 32 3 DataAdr [31:0] $end
$scope module dmem $end
$var wire 32 4 RD [31:0] $end
$var wire 1 , clk $end
$var wire 1 / WE $end
$var wire 32 5 WD [31:0] $end
$var wire 32 6 A [31:0] $end
$upscope $end
$scope module imem $end
$var wire 6 7 A [5:0] $end
$var wire 32 8 RD [31:0] $end
$upscope $end
$scope module mips $end
$var wire 1 , Clk $end
$var wire 32 9 Instr [31:0] $end
$var wire 32 : ReadData [31:0] $end
$var wire 1 - Reset $end
$var wire 1 ; Zero $end
$var wire 32 < WriteData [31:0] $end
$var wire 1 / WE $end
$var wire 1 = RegWrite $end
$var wire 1 > RegDst $end
$var wire 1 ? PCSrc $end
$var wire 32 @ PC [31:0] $end
$var wire 1 A MemToReg $end
$var wire 1 B Jump $end
$var wire 1 C ALUSrc $end
$var wire 32 D ALUOut [31:0] $end
$var wire 3 E ALUControl [2:0] $end
$scope module control $end
$var wire 6 F Funct [5:0] $end
$var wire 6 G Opcode [5:0] $end
$var wire 1 ? PCSrc $end
$var wire 1 ; Zero $end
$var wire 1 = RegWrite $end
$var wire 1 > RegDst $end
$var wire 1 A MemtoReg $end
$var wire 1 / MemWrite $end
$var wire 1 B Jump $end
$var wire 1 H Branch $end
$var wire 1 C ALUSrc $end
$var wire 2 I ALUOp [1:0] $end
$var wire 3 J ALUControl [2:0] $end
$scope module aludec1 $end
$var wire 6 K funct [5:0] $end
$var wire 2 L AluOP [1:0] $end
$var reg 3 M AluControl [2:0] $end
$upscope $end
$scope module md1 $end
$var wire 6 N Opcode [5:0] $end
$var wire 1 = RegWrite $end
$var wire 1 > RegDst $end
$var wire 1 A MemtoReg $end
$var wire 1 / MemWrite $end
$var wire 1 B Jump $end
$var wire 1 H Branch $end
$var wire 1 C ALUSrc $end
$var wire 2 O ALUOp [1:0] $end
$var reg 9 P controls [8:0] $end
$upscope $end
$upscope $end
$scope module dp $end
$var wire 3 Q ALUControl [2:0] $end
$var wire 1 C ALUSrc $end
$var wire 1 , Clk $end
$var wire 32 R Instr [31:0] $end
$var wire 1 B Jump $end
$var wire 1 A MemtoReg $end
$var wire 1 ? PCSrc $end
$var wire 32 S ReadData [31:0] $end
$var wire 1 > RegDst $end
$var wire 1 = RegWrite $end
$var wire 1 - Reset $end
$var wire 32 T SrcA [31:0] $end
$var wire 1 ; Zero $end
$var wire 32 U WriteData [31:0] $end
$var wire 32 V SrcB [31:0] $end
$var wire 32 W SignImmSh [31:0] $end
$var wire 32 X SignImm [31:0] $end
$var wire 32 Y Result [31:0] $end
$var wire 5 Z RegisterAddress [4:0] $end
$var wire 32 [ PCPlus4 [31:0] $end
$var wire 32 \ PCNextbr [31:0] $end
$var wire 32 ] PCNext [31:0] $end
$var wire 32 ^ PCBranch [31:0] $end
$var wire 32 _ PC [31:0] $end
$var wire 32 ` ALUOut [31:0] $end
$scope module A3Mux $end
$var wire 5 a D0 [4:0] $end
$var wire 5 b D1 [4:0] $end
$var wire 1 > sel $end
$var wire 5 c out [4:0] $end
$upscope $end
$scope module PCRegister $end
$var wire 1 , clk $end
$var wire 1 - reset $end
$var wire 32 d D [31:0] $end
$var reg 32 e Q [31:0] $end
$upscope $end
$scope module SRCBmux $end
$var wire 1 C sel $end
$var wire 32 f out [31:0] $end
$var wire 32 g D1 [31:0] $end
$var wire 32 h D0 [31:0] $end
$upscope $end
$scope module WD3Mux $end
$var wire 32 i D1 [31:0] $end
$var wire 1 A sel $end
$var wire 32 j out [31:0] $end
$var wire 32 k D0 [31:0] $end
$upscope $end
$scope module alu_main $end
$var wire 3 l ALUControl [2:0] $end
$var wire 32 m N0 [31:0] $end
$var wire 32 n N1 [31:0] $end
$var wire 32 o SrcA [31:0] $end
$var wire 32 p SrcB [31:0] $end
$var wire 32 q SrcB_not [31:0] $end
$var wire 32 r mux1_out [31:0] $end
$var wire 32 s N3 [31:0] $end
$var wire 32 t N2 [31:0] $end
$var wire 1 u C_out $end
$var wire 32 v ALUResult [31:0] $end
$var reg 1 ; Zero $end
$scope module add1 $end
$var wire 32 w SrcB [31:0] $end
$var wire 32 x Y [31:0] $end
$var wire 32 y SrcA [31:0] $end
$var wire 1 u C_out $end
$upscope $end
$scope module mux1 $end
$var wire 32 z D0 [31:0] $end
$var wire 32 { D1 [31:0] $end
$var wire 1 | sel $end
$var wire 32 } out [31:0] $end
$upscope $end
$scope module mux2 $end
$var wire 32 ~ D0 [31:0] $end
$var wire 32 !" D1 [31:0] $end
$var wire 32 "" D2 [31:0] $end
$var wire 32 #" D3 [31:0] $end
$var wire 2 $" sel [1:0] $end
$var wire 32 %" out [31:0] $end
$upscope $end
$upscope $end
$scope module immsh $end
$var wire 32 &" shifted_out [31:0] $end
$var wire 32 '" shift_in [31:0] $end
$upscope $end
$scope module pcadd1 $end
$var wire 32 (" SrcA [31:0] $end
$var wire 32 )" SrcB [31:0] $end
$var wire 32 *" Y [31:0] $end
$var wire 1 +" C_out $end
$upscope $end
$scope module pcadd2 $end
$var wire 32 ," SrcA [31:0] $end
$var wire 32 -" SrcB [31:0] $end
$var wire 32 ." Y [31:0] $end
$var wire 1 /" C_out $end
$upscope $end
$scope module pcbrmux $end
$var wire 32 0" D0 [31:0] $end
$var wire 32 1" D1 [31:0] $end
$var wire 1 ? sel $end
$var wire 32 2" out [31:0] $end
$upscope $end
$scope module pcmux $end
$var wire 32 3" D0 [31:0] $end
$var wire 32 4" D1 [31:0] $end
$var wire 1 B sel $end
$var wire 32 5" out [31:0] $end
$upscope $end
$scope module rf $end
$var wire 5 6" A1 [4:0] $end
$var wire 5 7" A2 [4:0] $end
$var wire 5 8" A3 [4:0] $end
$var wire 32 9" RD1 [31:0] $end
$var wire 32 :" RD2 [31:0] $end
$var wire 32 ;" WD3 [31:0] $end
$var wire 1 = WE3 $end
$var wire 1 , clk $end
$upscope $end
$scope module se $end
$var wire 16 <" extend [15:0] $end
$var wire 32 =" extended [31:0] $end
$upscope $end
$upscope $end
$upscope $end
$upscope $end
$enddefinitions $end
#0
$dumpvars
bx ="
bx <"
bx ;"
bx :"
bx 9"
bx 8"
bx 7"
bx 6"
bx 5"
bx00 4"
bx 3"
bx 2"
bx 1"
bx 0"
x/"
bx ."
bx -"
bx00 ,"
x+"
bx *"
bx )"
b100 ("
bx '"
bx00 &"
bx %"
bx $"
b0xxxxxxxxxxxxxxxxxxxxxxxxxxxxxxx #"
bx ""
bx !"
bx ~
bx }
x|
bx {
bx z
bx y
bx x
bx w
bx v
xu
bx t
b0xxxxxxxxxxxxxxxxxxxxxxxxxxxxxxx s
bx r
bx q
bx p
bx o
bx n
bx m
bx l
bx k
bx j
bx i
bx h
bx g
bx f
bx e
bx d
bx c
bx b
bx a
bx `
bx _
bx ^
bx ]
bx \
bx [
bx Z
bx Y
bx X
bx00 W
bx V
bx U
bx T
bx S
bx R
bx Q
bx P
bx O
bx N
bx M
bx L
bx K
bx J
bx I
xH
bx G
bx F
bx E
bx D
xC
xB
xA
bx @
x?
x>
x=
bx <
x;
bx :
bx 9
bx 8
bx 7
bx 6
bx 5
bx 4
bx 3
bx 2
bx 1
bx 0
x/
bx .
z-
z,
b0 +
b100000000000100000000000000101 *
b0 )
b0 (
b100000000000100000000000000101 '
bx &
bz %
bz $
bx #
bz "
bz !
$end
#10
b100000000000110000000000001100 '
b100000000000110000000000001100 *
b1 (
b1 )
b1 +
#20
b100000011001111111111111110111 '
b100000011001111111111111110111 *
b10 (
b10 )
b10 +
#30
b111000100010000000100101 '
b111000100010000000100101 *
b11 (
b11 )
b11 +
#40
b11001000010100000100100 '
b11001000010100000100100 *
b100 (
b100 )
b100 +
#50
b101001000010100000100000 '
b101001000010100000100000 *
b101 (
b101 )
b101 +
#60
b10000101001110000000000001010 '
b10000101001110000000000001010 *
b110 (
b110 )
b110 +
#70
b11001000010000000101010 '
b11001000010000000101010 *
b111 (
b111 )
b111 +
#80
b10000100000000000000000000001 '
b10000100000000000000000000001 *
b1000 (
b1000 )
b1000 +
#90
b100000000001010000000000000000 '
b100000000001010000000000000000 *
b1001 (
b1001 )
b1001 +
#100
b111000100010000000101010 '
b111000100010000000101010 *
b1010 (
b1010 )
b1010 +
#110
b100001010011100000100000 '
b100001010011100000100000 *
b1011 (
b1011 )
b1011 +
#120
b111000100011100000100010 '
b111000100011100000100010 *
b1100 (
b1100 )
b1100 +
#130
b10101100011001110000000001000100 '
b10101100011001110000000001000100 *
b1101 (
b1101 )
b1101 +
#140
b10001100000000100000000001010000 '
b10001100000000100000000001010000 *
b1110 (
b1110 )
b1110 +
#150
b1000000000000000000000010001 '
b1000000000000000000000010001 *
b1111 (
b1111 )
b1111 +
#160
b100000000000100000000000000001 '
b100000000000100000000000000001 *
b10000 (
b10000 )
b10000 +
#170
b10101100000000100000000001010100 '
b10101100000000100000000001010100 *
b10001 (
b10001 )
b10001 +
#180
bx '
bx *
b10010 (
b10010 )
b10010 +
#190
b10011 (
b10011 )
b10011 +
#200
b10100 (
b10100 )
b10100 +
#210
b10101 (
b10101 )
b10101 +
#220
b10110 (
b10110 )
b10110 +
#230
b10111 (
b10111 )
b10111 +
#240
b11000 (
b11000 )
b11000 +
#250
b11001 (
b11001 )
b11001 +
#260
b11010 (
b11010 )
b11010 +
#270
b11011 (
b11011 )
b11011 +
#280
b11100 (
b11100 )
b11100 +
#290
b11101 (
b11101 )
b11101 +
#300
b11110 (
b11110 )
b11110 +
#310
b11111 (
b11111 )
b11111 +
#320
b100000 (
b100000 )
b100000 +
#330
b100001 (
b100001 )
b100001 +
#340
b100010 (
b100010 )
b100010 +
#350
b100011 (
b100011 )
b100011 +
#360
b100100 (
b100100 )
b100100 +
#370
b100101 (
b100101 )
b100101 +
#380
b100110 (
b100110 )
b100110 +
#390
b100111 (
b100111 )
b100111 +
#400
b101000 (
b101000 )
b101000 +
#410
b101001 (
b101001 )
b101001 +
#420
b101010 (
b101010 )
b101010 +
#430
b101011 (
b101011 )
b101011 +
#440
b101100 (
b101100 )
b101100 +
#450
b101101 (
b101101 )
b101101 +
#460
b101110 (
b101110 )
b101110 +
#470
b101111 (
b101111 )
b101111 +
#480
b110000 (
b110000 )
b110000 +
#490
b110001 (
b110001 )
b110001 +
#500
b110010 (
b110010 )
b110010 +
#510
b110011 (
b110011 )
b110011 +
#520
b110100 (
b110100 )
b110100 +
#530
b110101 (
b110101 )
b110101 +
#540
b110110 (
b110110 )
b110110 +
#550
b110111 (
b110111 )
b110111 +
#560
b111000 (
b111000 )
b111000 +
#570
b111001 (
b111001 )
b111001 +
#580
b111010 (
b111010 )
b111010 +
#590
b111011 (
b111011 )
b111011 +
#600
b111100 (
b111100 )
b111100 +
#610
b111101 (
b111101 )
b111101 +
#620
b111110 (
b111110 )
b111110 +
#630
b111111 (
b111111 )
b111111 +
#640
b100000000000100000000000000101 '
b100000000000100000000000000101 *
b0 (
b0 )
b1000000 +
#650
b100000000000110000000000001100 '
b100000000000110000000000001100 *
b1 (
b1 )
b1000001 +
#660
b100000011001111111111111110111 '
b100000011001111111111111110111 *
b10 (
b10 )
b1000010 +
#670
b111000100010000000100101 '
b111000100010000000100101 *
b11 (
b11 )
b1000011 +
#680
b11001000010100000100100 '
b11001000010100000100100 *
b100 (
b100 )
b1000100 +
#690
b101001000010100000100000 '
b101001000010100000100000 *
b101 (
b101 )
b1000101 +
#700
b10000101001110000000000001010 '
b10000101001110000000000001010 *
b110 (
b110 )
b1000110 +
#710
b11001000010000000101010 '
b11001000010000000101010 *
b111 (
b111 )
b1000111 +
#720
b10000100000000000000000000001 '
b10000100000000000000000000001 *
b1000 (
b1000 )
b1001000 +
#730
b100000000001010000000000000000 '
b100000000001010000000000000000 *
b1001 (
b1001 )
b1001001 +
#740
b111000100010000000101010 '
b111000100010000000101010 *
b1010 (
b1010 )
b1001010 +
#750
b100001010011100000100000 '
b100001010011100000100000 *
b1011 (
b1011 )
b1001011 +
#760
b111000100011100000100010 '
b111000100011100000100010 *
b1100 (
b1100 )
b1001100 +
#770
b10101100011001110000000001000100 '
b10101100011001110000000001000100 *
b1101 (
b1101 )
b1001101 +
#780
b10001100000000100000000001010000 '
b10001100000000100000000001010000 *
b1110 (
b1110 )
b1001110 +
#790
b1000000000000000000000010001 '
b1000000000000000000000010001 *
b1111 (
b1111 )
b1001111 +
#800
b100000000000100000000000000001 '
b100000000000100000000000000001 *
b10000 (
b10000 )
b1010000 +
#810
b10101100000000100000000001010100 '
b10101100000000100000000001010100 *
b10001 (
b10001 )
b1010001 +
#820
bx '
bx *
b10010 (
b10010 )
b1010010 +
#830
b10011 (
b10011 )
b1010011 +
#840
b10100 (
b10100 )
b1010100 +
#850
b10101 (
b10101 )
b1010101 +
#860
b10110 (
b10110 )
b1010110 +
#870
b10111 (
b10111 )
b1010111 +
#880
b11000 (
b11000 )
b1011000 +
#890
b11001 (
b11001 )
b1011001 +
#900
b11010 (
b11010 )
b1011010 +
#910
b11011 (
b11011 )
b1011011 +
#920
b11100 (
b11100 )
b1011100 +
#930
b11101 (
b11101 )
b1011101 +
#940
b11110 (
b11110 )
b1011110 +
#950
b11111 (
b11111 )
b1011111 +
#960
b100000 (
b100000 )
b1100000 +
#970
b100001 (
b100001 )
b1100001 +
#980
b100010 (
b100010 )
b1100010 +
#990
b100011 (
b100011 )
b1100011 +
#1000
b100100 (
b100100 )
b1100100 +
#1010
b100101 (
b100101 )
b1100101 +
#1020
b100110 (
b100110 )
b1100110 +
#1030
b100111 (
b100111 )
b1100111 +
#1040
b101000 (
b101000 )
b1101000 +
#1050
b101001 (
b101001 )
b1101001 +
#1060
b101010 (
b101010 )
b1101010 +
#1070
b101011 (
b101011 )
b1101011 +
#1080
b101100 (
b101100 )
b1101100 +
#1090
b101101 (
b101101 )
b1101101 +
#1100
b101110 (
b101110 )
b1101110 +
#1110
b101111 (
b101111 )
b1101111 +
#1120
b110000 (
b110000 )
b1110000 +
#1130
b110001 (
b110001 )
b1110001 +
#1140
b110010 (
b110010 )
b1110010 +
#1150
b110011 (
b110011 )
b1110011 +
#1160
b110100 (
b110100 )
b1110100 +
#1170
b110101 (
b110101 )
b1110101 +
#1180
b110110 (
b110110 )
b1110110 +
#1190
b110111 (
b110111 )
b1110111 +
#1200
b111000 (
b111000 )
b1111000 +
#1210
b111001 (
b111001 )
b1111001 +
#1220
b111010 (
b111010 )
b1111010 +
#1230
b111011 (
b111011 )
b1111011 +
#1240
b111100 (
b111100 )
b1111100 +
#1250
b111101 (
b111101 )
b1111101 +
#1260
b111110 (
b111110 )
b1111110 +
#1270
b111111 (
b111111 )
b1111111 +
#1280
b100000000000100000000000000101 '
b100000000000100000000000000101 *
b0 (
b0 )
b10000000 +
#1290
b100000000000110000000000001100 '
b100000000000110000000000001100 *
b1 (
b1 )
b10000001 +
#1300
b100000011001111111111111110111 '
b100000011001111111111111110111 *
b10 (
b10 )
b10000010 +
#1310
b111000100010000000100101 '
b111000100010000000100101 *
b11 (
b11 )
b10000011 +
#1320
b11001000010100000100100 '
b11001000010100000100100 *
b100 (
b100 )
b10000100 +
#1330
b101001000010100000100000 '
b101001000010100000100000 *
b101 (
b101 )
b10000101 +
#1340
b10000101001110000000000001010 '
b10000101001110000000000001010 *
b110 (
b110 )
b10000110 +
#1350
b11001000010000000101010 '
b11001000010000000101010 *
b111 (
b111 )
b10000111 +
#1360
b10000100000000000000000000001 '
b10000100000000000000000000001 *
b1000 (
b1000 )
b10001000 +
#1370
b100000000001010000000000000000 '
b100000000001010000000000000000 *
b1001 (
b1001 )
b10001001 +
#1380
b111000100010000000101010 '
b111000100010000000101010 *
b1010 (
b1010 )
b10001010 +
#1390
b100001010011100000100000 '
b100001010011100000100000 *
b1011 (
b1011 )
b10001011 +
#1400
b111000100011100000100010 '
b111000100011100000100010 *
b1100 (
b1100 )
b10001100 +
#1410
b10101100011001110000000001000100 '
b10101100011001110000000001000100 *
b1101 (
b1101 )
b10001101 +
#1420
b10001100000000100000000001010000 '
b10001100000000100000000001010000 *
b1110 (
b1110 )
b10001110 +
#1430
b1000000000000000000000010001 '
b1000000000000000000000010001 *
b1111 (
b1111 )
b10001111 +
#1440
b100000000000100000000000000001 '
b100000000000100000000000000001 *
b10000 (
b10000 )
b10010000 +
#1450
b10101100000000100000000001010100 '
b10101100000000100000000001010100 *
b10001 (
b10001 )
b10010001 +
#1460
bx '
bx *
b10010 (
b10010 )
b10010010 +
#1470
b10011 (
b10011 )
b10010011 +
#1480
b10100 (
b10100 )
b10010100 +
#1490
b10101 (
b10101 )
b10010101 +
#1500
b10110 (
b10110 )
b10010110 +
#1510
b10111 (
b10111 )
b10010111 +
#1520
b11000 (
b11000 )
b10011000 +
#1530
b11001 (
b11001 )
b10011001 +
#1540
b11010 (
b11010 )
b10011010 +
#1550
b11011 (
b11011 )
b10011011 +
#1560
b11100 (
b11100 )
b10011100 +
#1570
b11101 (
b11101 )
b10011101 +
#1580
b11110 (
b11110 )
b10011110 +
#1590
b11111 (
b11111 )
b10011111 +
#1600
b100000 (
b100000 )
b10100000 +
#1610
b100001 (
b100001 )
b10100001 +
#1620
b100010 (
b100010 )
b10100010 +
#1630
b100011 (
b100011 )
b10100011 +
#1640
b100100 (
b100100 )
b10100100 +
#1650
b100101 (
b100101 )
b10100101 +
#1660
b100110 (
b100110 )
b10100110 +
#1670
b100111 (
b100111 )
b10100111 +
#1680
b101000 (
b101000 )
b10101000 +
#1690
b101001 (
b101001 )
b10101001 +
#1700
b101010 (
b101010 )
b10101010 +
#1710
b101011 (
b101011 )
b10101011 +
#1720
b101100 (
b101100 )
b10101100 +
#1730
b101101 (
b101101 )
b10101101 +
#1740
b101110 (
b101110 )
b10101110 +
#1750
b101111 (
b101111 )
b10101111 +
#1760
b110000 (
b110000 )
b10110000 +
#1770
b110001 (
b110001 )
b10110001 +
#1780
b110010 (
b110010 )
b10110010 +
#1790
b110011 (
b110011 )
b10110011 +
#1800
b110100 (
b110100 )
b10110100 +
#1810
b110101 (
b110101 )
b10110101 +
#1820
b110110 (
b110110 )
b10110110 +
#1830
b110111 (
b110111 )
b10110111 +
#1840
b111000 (
b111000 )
b10111000 +
