Unpipelined/MIPS_core_tb.v
`timescale 1ns / 1ns
`include "MIPS_Single_Cycle.v"

module testbench;
    reg clk;
    reg reset;
    wire [31:0] writedata, dataadr;
    wire memwrite;
// instantiate device to be tested
    top dut (clk, reset, writedata, dataadr, memwrite);
// initialize test




    initial begin
        $dumpfile("top.vcd");
        $dumpvars;
    end






    initial
        begin
            reset <= 1; # 22; reset <=0;
        end


// generate clock to sequence tests
    always begin
            clk <=1; # 5; clk <=0; # 5;
            
        end


// check results
    always @ (negedge clk)
        begin
            if (memwrite) begin
                if (dataadr === 84 & writedata === 7) begin
                    $display ("Simulation succeeded");
                    $stop;
                end else if (dataadr !==80) begin
                    $display ("Simulation failed");
                    $stop;
            end
        end
    end
endmodule

Unpipelined/MIPS_Single_Cycle.v
//on reset PC should begin at 0xBFC0 0000



//32 bit flip flop with active high reset 
module Dflipflop(Q, Clk, D, reset);

    input Clk, reset; 
    input [31:0] D;
    output reg [31:0] Q;

    always @ (posedge Clk,posedge reset)
        if(reset==1) Q<=0;
        else Q<=D; //output new PC from alu on posedge Clk 
endmodule


module flopr #(parameter WIDTH = 8) (Clk,Reset, d, q);

    input Clk, Reset;
    input [WIDTH-1:0] d;
    output reg [WIDTH-1:0] q;

    
    always @ (posedge Clk,posedge Reset)
        if(Reset) q<=0;
        else q<=d; //output new PC from alu on posedge Clk 
endmodule


module mux2 #(parameter WIDTH = 8) (d0,d1,s,y);

    input [WIDTH-1:0] d0, d1;
    input s;
    output [WIDTH-1:0] y;

    assign y=s?d1:d0;

endmodule


//register file. Contains 32 internal registers. each 32 bits wide
//address 1 (A1) is read to RD1 asynchronously. Same is true for A2 and RD2.
//To write, input address is A3. Address to read is WD3. occurs on posedge Clk
//write enable must also be active. 
module registerFile(Clk,WE3,A1,A2,A3,WD3,RD1,RD2);
    
    output [31:0] RD1, RD2;  //outputs of the register file are each 32 bits since the regsiter is 32 bits wide
    input [4:0] A1,A2,A3;   //2^5=32 since 32 total addresses
    input [31:0] WD3; //the data to be written if WE3 is high 
    input Clk, WE3; 

    reg [31:0] internal_mem [31:0]; //32 wires each 32 bits long

    
        always @ (posedge Clk) 
            if (WE3) internal_mem[A3]<=WD3;
        

    assign RD1 = (A1 !=0) ? internal_mem[A1] :0;
    assign RD2 = (A2 !=0) ? internal_mem[A2] :0;

endmodule


//in single cycle mips architecture, the program and variables are stored in
//two seperate registers. Instruction memory stores the program, Data memory
//(TBD) stores variable information
module Instruction_memory(A, RD);
    output [31:0] RD;    //output data is 32 bits wide because thats how long Instructions are
    input [5:0] A;      //64 possible addresses

    reg [31:0] RAM [63:0]; //64 wires each 32 bits wide
    
    initial
        begin 
            $readmemh("memfile.dat",RAM); //read dissassembled MIPS code and load it into ram
    end

    assign RD = RAM[A]; //output onto bus. no need for clock because ram is asynchronous

endmodule




//more ram. This is where data is written during program exectuion. 
//writing is done on the clock, reading is done asynchronously
//input address is 32 bits, data width is 32 bits. 
module data_memory(Clk, WE, A, WD, RD);
    //not using full memory capabilities
    //

    output reg [31:0] RD;
    input Clk, WE;
    input [31:0] A,WD;


    reg [31:0] data [63:0];


//    assign RD = data[A[31:2]]; //address is always being read out

  //  always @ (posedge Clk)
    //    if(WE==1) data[A[31:2]] <=WD;

    always @(*) begin
        RD<=data[A[31:2]];
    end

    //assign RD=data[A[31:2]];

    always @ (posedge Clk)
        if(WE) data[A[31:2]] <=WD;

endmodule



module SignExtender(extend, extended);

    input [15:0] extend;
    output [31:0] extended;

    assign extended[31:0]= {{16{extend[15]}},extend[15:0]};

endmodule

module adder(Y,C_out,C_in,SrcA, SrcB);

    output [31:0] Y;
    output C_out;
    input [31:0] SrcA, SrcB;
    input C_in;
    

    assign {C_out,Y}=SrcA+SrcB+C_in;


endmodule



//The input to the alu control logic depends on 2 things, the op code and the
//funct space (in R type Instructions). For instance, an Instruction with
//opcode 000000 is always going to have an AluOp of 10. 10 indicates that the
//ALUControl depends on the funct field of the Instruction, (Or, Nor, Add all
//work differently). However, in I type Instructions, there is no funct field,
//so the alu controll only depends on the opcode, and the logic for that is
//quite straight forward. 

//ALU decoder controls the operation that occurs in the alu
module AluDecoder(Funct,AluOP,ALUControl);

    output reg [2:0]ALUControl;
    input [1:0] AluOP;
    input [5:0] Funct;
    

    always @ (*)
        case (AluOP)
            2'b00: ALUControl <=3'b010;
            2'b01: ALUControl <=3'b110;
            default: case(Funct)
                6'b100000 : ALUControl <= 3'b010;   //add
                6'b100010 : ALUControl <= 3'b110;   //sub
                6'b100100 : ALUControl <= 3'b000;   //and
                6'b100101 : ALUControl <= 3'b001;   //or
                6'b101010 : ALUControl <= 3'b111;   //slt
                default: ALUControl <=3'bxxx;
            endcase
        endcase


        
endmodule



module Or(Y, SrcA,SrcB);

    output [31:0] Y;
    input [31:0] SrcA, SrcB;


    assign Y=SrcA | SrcB;

endmodule

module And(Y, SrcA,SrcB);

    output [31:0] Y;
    input [31:0] SrcA, SrcB;


    assign Y=SrcA & SrcB;

endmodule
//subtract and add are done the same exact way. the only difference is that 
//subtract is compiled as the addition of a twos complement number to
//a posative 
module ALU(Zero, ALUResult, C_out, ALUControl, SrcA, SrcB);

    output Zero;
    output [31:0] ALUResult;
    output C_out;
    input [2:0] ALUControl;
    input [31:0] SrcA, SrcB;
    
    wire [31:0] SrcB_not; assign SrcB_not=~SrcB;
    wire [31:0] mux1_out;
    wire [31:0] N0,N1,N2,N3;


    mux_2_32b mux1(mux1_out,ALUControl[2], SrcB,SrcB_not);
 
    assign N0=mux1_out&SrcA;

    assign N1=mux1_out|SrcA;


    adder add1(N2,C_out,ALUControl[2],mux1_out,SrcA);
    assign N3={N2[31]};

    mux_4_32b mux2(ALUResult,ALUControl[1:0],N0,N1,N2,N3);


    assign Zero = (ALUResult==0) ?   1 :0;

endmodule








module shift_left_2(shifted_out,shift_in);

    input [31:0] shift_in;
    output [31:0] shifted_out;


    assign shifted_out=shift_in<<2;
endmodule


module mux_2_32b(out, sel, D0, D1);

    output [31:0] out;
    input sel;
    input [31:0] D0, D1;
    
    assign out=sel? D1:D0;

endmodule


module mux_4_32b(out, sel, D0, D1, D2, D3);

    output [31:0] out;
    input [1:0]sel;
    input [31:0] D0, D1, D2, D3;
    
    assign out=sel[1]? (sel[0]?D3:D2):(sel[0]? D1: D0);

endmodule




//The main decoder for the system. Seperate from ALU decoder. This can be
//viewed as the microcode of the system for each Instruction. 
module mainDecoder(Opcode,MemtoReg,MemWrite,Branch,ALUSrc,RegDst,RegWrite,Jump,ALUOp);


    output MemWrite, RegWrite, RegDst, ALUSrc, MemtoReg, Branch, Jump;
    output [1:0] ALUOp;
    input [5:0] Opcode;

    reg [8:0] controls;


    assign {RegWrite,RegDst,ALUSrc,Branch,MemWrite,MemtoReg,Jump,ALUOp}=controls;

    always @(*)
        if(Opcode==6'b000000) controls<=9'b110000010;
        else if(Opcode==6'b100011) controls<=9'b101001000;           
        else if (Opcode==6'b101011) controls<=9'b001010000;
        else if (Opcode==6'b000100) controls<=9'b000100001;
        else if (Opcode==6'b001000) controls<=9'b101000000;
        else if (Opcode==6'b000010) controls<=9'b000000100;
        else controls<=9'bxxxxxxxxx;
endmodule




module controller (Opcode,Funct,Zero,MemtoReg,MemWrite,PCSrc,ALUSrc,RegDst,RegWrite,Jump,ALUControl);





    
    output [2:0] ALUControl;
    output PCSrc, MemtoReg, ALUSrc, RegDst, RegWrite, MemWrite,Jump;

    input [5:0] Funct;
    input [5:0] Opcode;
    input Zero;
    
    wire Branch;
    wire [1:0] ALUOp;


    mainDecoder md1(Opcode,MemtoReg,MemWrite,Branch,ALUSrc,RegDst,RegWrite,Jump,ALUOp);

    AluDecoder aludec1(Funct,ALUOp,ALUControl);

    
    assign PCSrc=Branch & Zero; //source of PC. /\


endmodule



module datapath(Clk,Reset,MemtoReg,PCSrc,ALUSrc,RegDst,RegWrite,Jump,ALUControl,Zero,PC,Instr,ALUOut,WriteData,ReadData);

    output Zero; //Zero flag if alu output is 0
    output [31:0] PC; //program counter output after selection (final PC for Instruction retrieving)
    output [31:0] ALUOut, WriteData;
    
    input Reset, Clk, MemtoReg, PCSrc, ALUSrc, RegDst, RegWrite, Jump;
    input [2:0] ALUControl; 
    input [31:0] ReadData; //inputs datat to datapath
    input [31:0] Instr;

    wire [4:0] WriteReg; //address if writing to registers (A3)
    
    
    wire [31:0] PCNext, PCNextbr, PCPlus4, PCBranch; 
    //PCPLUS4 is the output of the ALU after adding 4
    //PCBranch is the PC value after a branch Instruction (which uses relative addressing)
    //PCNextbr is the output of the mux after selecting between branching and just adding 4
    
    //PCNext is the value of the PC that is stored in the PC regitser

    wire [31:0] SignImm, SignImmSh;
    //a branch may be posative or negative. Since the PC is 32 bits and the
    //largest possible relative address is 16 bits, it must be extended to 32
    //bits with the correct sign in mind. 
    //SignImm is the unextended branch value (relative address) and SignImmSh
    //is the sign extended relative address inputted to the PC ALU

    wire [31:0] SrcA, SrcB; 
    //inputs to the main ALU

    wire [31:0] Result;
    //This is not the alu resut, it is the output of the mux that selects
    //between data memory outout and ALUOutput. This is imporatnt as it
    //determines what is written to the register file
    

    flopr #(32) PCRegister(Clk,Reset,PCNext,PC);
    //PCRegister


    adder pcadd1(PCPlus4,,1'b0,32'b100,PC); //the adder for the Program counter iteration

    shift_left_2 immsh(SignImmSh,SignImm);
    //shiftng for branch operatioms (multiply by 4)

    adder pcadd2 (PCBranch,,1'b0,SignImmSh,PCPlus4);
    //the adder for branch operations. number of bytes+PC
    


    mux2 #(32) pcbrmux(PCPlus4,PCBranch,PCSrc,PCNextbr);

    //this mux determines if the PC should use the next address(PC+4) or the
    //branched PC (PCBranch) address based on contrrol logic from main dec


    
    mux2 #(32) pcmux (PCNextbr,{PCPlus4[31:28],Instr[25:0],2'b00},Jump,PCNext);



    registerFile rf(Clk,RegWrite, Instr[25:21],Instr[20:16],WriteReg,Result,SrcA,WriteData);  


    //mux_2_32b(out, sel, D0, D1); 
    mux2 #5 wrmux(Instr[20:16], Instr[15:11], RegDst, WriteReg);


    mux2 #32 resmux(ALUOut, ReadData, MemtoReg, Result);

    SignExtender se(Instr[15:0],SignImm);
    //ALU
    mux2 #(32) SrcBmux (WriteData,SignImm,ALUSrc,SrcB);
    
    wire C_out;

    ALU alu_main (Zero, ALUOut,C_out,ALUControl,SrcA, SrcB);


endmodule

module mux_2_5b(out, sel, D0, D1); //for controlling A3

    output [4:0] out;
    input sel;
    input [4:0] D0, D1;
    
    assign out=sel? D1:D0;

endmodule


module MIPS (Clk,reset,PC,Instr,memwrite,ALUOut,writedata,ReadData);


    input Clk, reset;
    input [31:0] Instr;
    input [31:0] ReadData;

    output [31:0] PC,ALUOut,writedata;
    output memwrite;



    wire MemToReg, Branch,ALUSrc, RegDst, RegWrite, Jump,PCSrc,Zero;
    wire [2:0] ALUControl;

    controller control(Instr[31:26],Instr[5:0],Zero,MemtoReg,memwrite,PCSrc,ALUSrc,RegDst,RegWrite,Jump,ALUControl);



    //datapath dp(ALUOut, WriteData, PC, Zero, Reset, Clk, ALUControl, PCSrc, MemToReg, ALUSrc, RegDst, RegWrite, Jump, ReadData,Instr);
    datapath dp(Clk,reset,MemtoReg,PCSrc,ALUSrc,RegDst,RegWrite,Jump,ALUControl,Zero,PC,Instr,ALUOut,writedata,ReadData);


endmodule


module top(Clk, Reset, WriteData,DataAdr,MemWrite);


    input Clk, Reset;
    output [31:0] WriteData, DataAdr;
    output MemWrite;


    wire [31:0] PC, Instr, ReadData;

    //MIPS (ALUOut,WriteData,WE, PC,Instr,ReadData,Reset,Clk);
    MIPS mips(Clk,Reset,PC,Instr,MemWrite,DataAdr,WriteData,ReadData);

    //Instruction_memory(RD, A);
    Instruction_memory imem(PC[7:2],Instr);



    //data_memory(RD,Clk,A,WD,WE);    
    data_memory dmem(Clk,MemWrite,DataAdr,WriteData,ReadData);

endmodule

Unpipelined/top.vcd
$date
	Sun Jun  5 17:34:57 2022
$end
$version
	Icarus Verilog
$end
$timescale
	1ns
$end
$scope module And $end
$var wire 32 ! SrcA [31:0] $end
$var wire 32 " SrcB [31:0] $end
$var wire 32 # Y [31:0] $end
$upscope $end
$scope module Dflipflop $end
$var wire 1 $ Clk $end
$var wire 32 % D [31:0] $end
$var wire 1 & reset $end
$var reg 32 ' Q [31:0] $end
$upscope $end
$scope module Or $end
$var wire 32 ( SrcA [31:0] $end
$var wire 32 ) SrcB [31:0] $end
$var wire 32 * Y [31:0] $end
$upscope $end
$scope module mux_2_5b $end
$var wire 5 + D0 [4:0] $end
$var wire 5 , D1 [4:0] $end
$var wire 1 - sel $end
$var wire 5 . out [4:0] $end
$upscope $end
$scope module testbench $end
$var wire 32 / writedata [31:0] $end
$var wire 1 0 memwrite $end
$var wire 32 1 dataadr [31:0] $end
$var reg 1 2 clk $end
$var reg 1 3 reset $end
$scope module dut $end
$var wire 1 2 Clk $end
$var wire 1 3 Reset $end
$var wire 32 4 WriteData [31:0] $end
$var wire 32 5 ReadData [31:0] $end
$var wire 32 6 PC [31:0] $end
$var wire 1 0 MemWrite $end
$var wire 32 7 Instr [31:0] $end
$var wire 32 8 DataAdr [31:0] $end
$scope module dmem $end
$var wire 1 2 Clk $end
$var wire 1 0 WE $end
$var wire 32 9 WD [31:0] $end
$var wire 32 : A [31:0] $end
$var reg 32 ; RD [31:0] $end
$upscope $end
$scope module imem $end
$var wire 6 < A [5:0] $end
$var wire 32 = RD [31:0] $end
$upscope $end
$scope module mips $end
$var wire 1 2 Clk $end
$var wire 32 > Instr [31:0] $end
$var wire 32 ? ReadData [31:0] $end
$var wire 1 3 reset $end
$var wire 32 @ writedata [31:0] $end
$var wire 1 0 memwrite $end
$var wire 1 A Zero $end
$var wire 1 B RegWrite $end
$var wire 1 C RegDst $end
$var wire 1 D PCSrc $end
$var wire 32 E PC [31:0] $end
$var wire 1 F MemtoReg $end
$var wire 1 G Jump $end
$var wire 1 H ALUSrc $end
$var wire 32 I ALUOut [31:0] $end
$var wire 3 J ALUControl [2:0] $end
$scope module control $end
$var wire 6 K Funct [5:0] $end
$var wire 6 L Opcode [5:0] $end
$var wire 1 D PCSrc $end
$var wire 1 A Zero $end
$var wire 1 B RegWrite $end
$var wire 1 C RegDst $end
$var wire 1 F MemtoReg $end
$var wire 1 0 MemWrite $end
$var wire 1 G Jump $end
$var wire 1 M Branch $end
$var wire 1 H ALUSrc $end
$var wire 2 N ALUOp [1:0] $end
$var wire 3 O ALUControl [2:0] $end
$scope module aludec1 $end
$var wire 6 P Funct [5:0] $end
$var wire 2 Q AluOP [1:0] $end
$var reg 3 R ALUControl [2:0] $end
$upscope $end
$scope module md1 $end
$var wire 6 S Opcode [5:0] $end
$var wire 1 B RegWrite $end
$var wire 1 C RegDst $end
$var wire 1 F MemtoReg $end
$var wire 1 0 MemWrite $end
$var wire 1 G Jump $end
$var wire 1 M Branch $end
$var wire 1 H ALUSrc $end
$var wire 2 T ALUOp [1:0] $end
$var reg 9 U controls [8:0] $end
$upscope $end
$upscope $end
$scope module dp $end
$var wire 3 V ALUControl [2:0] $end
$var wire 1 H ALUSrc $end
$var wire 1 2 Clk $end
$var wire 32 W Instr [31:0] $end
$var wire 1 G Jump $end
$var wire 1 F MemtoReg $end
$var wire 1 D PCSrc $end
$var wire 32 X ReadData [31:0] $end
$var wire 1 C RegDst $end
$var wire 1 B RegWrite $end
$var wire 1 3 Reset $end
$var wire 1 A Zero $end
$var wire 5 Y WriteReg [4:0] $end
$var wire 32 Z WriteData [31:0] $end
$var wire 32 [ SrcB [31:0] $end
$var wire 32 \ SrcA [31:0] $end
$var wire 32 ] SignImmSh [31:0] $end
$var wire 32 ^ SignImm [31:0] $end
$var wire 32 _ Result [31:0] $end
$var wire 32 ` PCPlus4 [31:0] $end
$var wire 32 a PCNextbr [31:0] $end
$var wire 32 b PCNext [31:0] $end
$var wire 32 c PCBranch [31:0] $end
$var wire 32 d PC [31:0] $end
$var wire 1 e C_out $end
$var wire 32 f ALUOut [31:0] $end
$scope module PCRegister $end
$var wire 1 2 Clk $end
$var wire 1 3 Reset $end
$var wire 32 g d [31:0] $end
$var reg 32 h q [31:0] $end
$upscope $end
$scope module SrcBmux $end
$var wire 1 H s $end
$var wire 32 i y [31:0] $end
$var wire 32 j d1 [31:0] $end
$var wire 32 k d0 [31:0] $end
$upscope $end
$scope module alu_main $end
$var wire 3 l ALUControl [2:0] $end
$var wire 32 m N0 [31:0] $end
$var wire 32 n N1 [31:0] $end
$var wire 32 o SrcB [31:0] $end
$var wire 32 p SrcB_not [31:0] $end
$var wire 32 q mux1_out [31:0] $end
$var wire 1 A Zero $end
$var wire 32 r SrcA [31:0] $end
$var wire 32 s N3 [31:0] $end
$var wire 32 t N2 [31:0] $end
$var wire 1 e C_out $end
$var wire 32 u ALUResult [31:0] $end
$scope module add1 $end
$var wire 1 v C_in $end
$var wire 32 w Y [31:0] $end
$var wire 32 x SrcB [31:0] $end
$var wire 32 y SrcA [31:0] $end
$var wire 1 e C_out $end
$upscope $end
$scope module mux1 $end
$var wire 32 z D0 [31:0] $end
$var wire 32 { D1 [31:0] $end
$var wire 1 | sel $end
$var wire 32 } out [31:0] $end
$upscope $end
$scope module mux2 $end
$var wire 32 ~ D0 [31:0] $end
$var wire 32 !" D1 [31:0] $end
$var wire 32 "" D2 [31:0] $end
$var wire 32 #" D3 [31:0] $end
$var wire 2 $" sel [1:0] $end
$var wire 32 %" out [31:0] $end
$upscope $end
$upscope $end
$scope module immsh $end
$var wire 32 &" shifted_out [31:0] $end
$var wire 32 '" shift_in [31:0] $end
$upscope $end
$scope module pcadd1 $end
$var wire 1 (" C_in $end
$var wire 32 )" SrcA [31:0] $end
$var wire 32 *" SrcB [31:0] $end
$var wire 32 +" Y [31:0] $end
$var wire 1 ," C_out $end
$upscope $end
$scope module pcadd2 $end
$var wire 1 -" C_in $end
$var wire 32 ." SrcA [31:0] $end
$var wire 32 /" SrcB [31:0] $end
$var wire 32 0" Y [31:0] $end
$var wire 1 1" C_out $end
$upscope $end
$scope module pcbrmux $end
$var wire 32 2" d0 [31:0] $end
$var wire 32 3" d1 [31:0] $end
$var wire 1 D s $end
$var wire 32 4" y [31:0] $end
$upscope $end
$scope module pcmux $end
$var wire 32 5" d0 [31:0] $end
$var wire 32 6" d1 [31:0] $end
$var wire 1 G s $end
$var wire 32 7" y [31:0] $end
$upscope $end
$scope module resmux $end
$var wire 32 8" d0 [31:0] $end
$var wire 32 9" d1 [31:0] $end
$var wire 1 F s $end
$var wire 32 :" y [31:0] $end
$upscope $end
$scope module rf $end
$var wire 5 ;" A1 [4:0] $end
$var wire 5 <" A2 [4:0] $end
$var wire 1 2 Clk $end
$var wire 32 =" WD3 [31:0] $end
$var wire 1 B WE3 $end
$var wire 32 >" RD2 [31:0] $end
$var wire 32 ?" RD1 [31:0] $end
$var wire 5 @" A3 [4:0] $end
$upscope $end
$scope module se $end
$var wire 16 A" extend [15:0] $end
$var wire 32 B" extended [31:0] $end
$upscope $end
$scope module wrmux $end
$var wire 5 C" d0 [4:0] $end
$var wire 5 D" d1 [4:0] $end
$var wire 1 C s $end
$var wire 5 E" y [4:0] $end
$upscope $end
$upscope $end
$upscope $end
$upscope $end
$upscope $end
$enddefinitions $end
#0
$dumpvars
b10 E"
b0 D"
b10 C"
b101 B"
b101 A"
b10 @"
b0 ?"
bx >"
b101 ="
b10 <"
b0 ;"
b101 :"
bx 9"
b101 8"
b100 7"
b10000000000000010100 6"
b100 5"
b100 4"
b11000 3"
b100 2"
01"
b11000 0"
b100 /"
b10100 ."
0-"
0,"
b100 +"
b0 *"
b100 )"
0("
b101 '"
b10100 &"
b101 %"
b10 $"
b0 #"
b101 ""
b101 !"
b0 ~
b101 }
0|
b11111111111111111111111111111010 {
b101 z
b101 y
b0 x
b101 w
0v
b101 u
b101 t
b0 s
b0 r
b101 q
b11111111111111111111111111111010 p
b101 o
b101 n
b0 m
b10 l
bx k
b101 j
b101 i
b0 h
b100 g
b101 f
0e
b0 d
b11000 c
b100 b
b100 a
b100 `
b101 _
b101 ^
b10100 ]
b0 \
b101 [
bx Z
b10 Y
bx X
b100000000000100000000000000101 W
b10 V
b101000000 U
b0 T
b1000 S
b10 R
b0 Q
b101 P
b10 O
b0 N
0M
b1000 L
b101 K
b10 J
b101 I
1H
0G
0F
b0 E
0D
0C
1B
0A
bx @
bx ?
b100000000000100000000000000101 >
b100000000000100000000000000101 =
b0 <
bx ;
b101 :
bx 9
b101 8
b100000000000100000000000000101 7
b0 6
bx 5
bx 4
13
12
b101 1
00
bx /
bz .
z-
bz ,
bz +
bx *
bz )
bz (
bx '
z&
bz %
z$
bx #
bz "
bz !
$end
#5
02
#10
b101 /
b101 4
b101 9
b101 @
b101 Z
b101 k
b101 >"
12
#15
02
#20
12
#22
03
#25
02
#30
b1100 _
b1100 :"
b1100 ="
b1100 1
b1100 8
b1100 :
b1100 I
b1100 f
b1100 u
b1100 %"
b1100 8"
b1100 t
b1100 w
b1100 ""
b1100 n
b1100 !"
b11111111111111111111111111110011 p
b11111111111111111111111111110011 {
b1100 q
b1100 y
b1100 }
b1000 b
b1000 g
b1000 7"
bx /
bx 4
bx 9
bx @
bx Z
bx k
bx >"
b11 Y
b11 @"
b11 E"
b110000 ]
b110000 &"
b110000 ."
b1100 [
b1100 i
b1100 o
b1100 z
b111000 c
b111000 0"
b111000 3"
b1000 a
b1000 4"
b1000 5"
b1100 K
b1100 P
b11000000000000110000 6"
b11 <"
b11 C"
b1100 ^
b1100 j
b1100 '"
b1100 B"
b1100 A"
b1000 `
b1000 +"
b1000 /"
b1000 2"
b100000000000110000000000001100 7
b100000000000110000000000001100 =
b100000000000110000000000001100 >
b100000000000110000000000001100 W
b1 <
b100 6
b100 E
b100 d
b100 h
b100 *"
12
#35
02
#40
b11 _
b11 :"
b11 ="
b11 1
b11 8
b11 :
b11 I
b11 f
b11 u
b11 %"
b11 8"
1e
b11 t
b11 w
b11 ""
b11111111111111111111111111111111 n
b11111111111111111111111111111111 !"
b100 m
b100 ~
b1000 p
b1000 {
b11111111111111111111111111110111 q
b11111111111111111111111111110111 y
b11111111111111111111111111110111 }
b1100 b
b1100 g
b1100 7"
b1100 \
b1100 r
b1100 x
b1100 ?"
b111 Y
b111 @"
b111 E"
b11111111111111111111111111011100 ]
b11111111111111111111111111011100 &"
b11111111111111111111111111011100 ."
b11111111111111111111111111110111 [
b11111111111111111111111111110111 i
b11111111111111111111111111110111 o
b11111111111111111111111111110111 z
b11111111111111111111111111101000 c
b11111111111111111111111111101000 0"
b11111111111111111111111111101000 3"
b1100 a
b1100 4"
b1100 5"
b110111 K
b110111 P
b1100111111111111111011100 6"
b11 ;"
b111 <"
b111 C"
b11111 D"
b11111111111111111111111111110111 ^
b11111111111111111111111111110111 j
b11111111111111111111111111110111 '"
b11111111111111111111111111110111 B"
b1111111111110111 A"
bx /
bx 4
bx 9
bx @
bx Z
bx k
bx >"
b1100 `
b1100 +"
b1100 /"
b1100 2"
b100000011001111111111111110111 7
b100000011001111111111111110111 =
b100000011001111111111111110111 >
b100000011001111111111111110111 W
b10 <
b1000 6
b1000 E
b1000 d
b1000 h
b1000 *"
12
#45
02
#50
b1 $"
b1 J
b1 O
b1 R
b1 V
b1 l
1C
0H
b10 N
b10 Q
b10 T
b110000010 U
b111 _
b111 :"
b111 ="
b111 1
b111 8
b111 :
b111 I
b111 f
b111 u
b111 %"
b111 8"
b0 s
b0 #"
b1000 t
b1000 w
b1000 ""
0e
b111 n
b111 !"
b1 m
b1 ~
b11111111111111111111111111111010 p
b11111111111111111111111111111010 {
b101 q
b101 y
b101 }
b10000 b
b10000 g
b10000 7"
b11 \
b11 r
b11 x
b11 ?"
b100 Y
b100 @"
b100 E"
b1000000010010100 ]
b1000000010010100 &"
b1000000010010100 ."
b101 [
b101 i
b101 o
b101 z
b1000000010100100 c
b1000000010100100 0"
b1000000010100100 3"
b10000 a
b10000 4"
b10000 5"
b0 L
b0 S
b100101 K
b100101 P
b11100010001000000010010100 6"
b111 ;"
b10 <"
b10 C"
b100 D"
b10000000100101 ^
b10000000100101 j
b10000000100101 '"
b10000000100101 B"
b10000000100101 A"
b101 /
b101 4
b101 9
b101 @
b101 Z
b101 k
b101 >"
b10000 `
b10000 +"
b10000 /"
b10000 2"
b111000100010000000100101 7
b111000100010000000100101 =
b111000100010000000100101 >
b111000100010000000100101 W
b11 <
b1100 6
b1100 E
b1100 d
b1100 h
b1100 *"
12
#55
02
#60
b0 $"
b0 J
b0 O
b0 R
b0 V
b0 l
b100 _
b100 :"
b100 ="
b100 1
b100 8
b100 :
b100 I
b100 f
b100 u
b100 %"
b100 8"
b11111111111111111111111111111000 p
b11111111111111111111111111111000 {
b111 q
b111 y
b111 }
b10011 t
b10011 w
b10011 ""
b1111 n
b1111 !"
b100 m
b100 ~
b111 [
b111 i
b111 o
b111 z
b10100 b
b10100 g
b10100 7"
b1100 \
b1100 r
b1100 x
b1100 ?"
b111 /
b111 4
b111 9
b111 @
b111 Z
b111 k
b111 >"
b101 Y
b101 @"
b101 E"
b1010000010010000 ]
b1010000010010000 &"
b1010000010010000 ."
b1010000010100100 c
b1010000010100100 0"
b1010000010100100 3"
b10100 a
b10100 4"
b10100 5"
b100100 K
b100100 P
b1100100001010000010010000 6"
b11 ;"
b100 <"
b100 C"
b101 D"
b10100000100100 ^
b10100000100100 j
b10100000100100 '"
b10100000100100 B"
b10100000100100 A"
b10100 `
b10100 +"
b10100 /"
b10100 2"
b11001000010100000100100 7
b11001000010100000100100 =
b11001000010100000100100 >
b11001000010100000100100 W
b100 <
b10000 6
b10000 E
b10000 d
b10000 h
b10000 *"
12
#65
02
#70
b1011 _
b1011 :"
b1011 ="
b1011 1
b1011 8
b1011 :
b1011 I
b1011 f
b1011 u
b1011 %"
b1011 8"
b10 $"
b10 J
b10 O
b10 R
b10 V
b10 l
b1011 t
b1011 w
b1011 ""
b111 n
b111 !"
b11000 b
b11000 g
b11000 7"
b100 \
b100 r
b100 x
b100 ?"
b1010000010000000 ]
b1010000010000000 &"
b1010000010000000 ."
b1010000010011000 c
b1010000010011000 0"
b1010000010011000 3"
b11000 a
b11000 4"
b11000 5"
b100000 K
b100000 P
b10100100001010000010000000 6"
b101 ;"
b10100000100000 ^
b10100000100000 j
b10100000100000 '"
b10100000100000 B"
b10100000100000 A"
b11000 `
b11000 +"
b11000 /"
b11000 2"
b101001000010100000100000 7
b101001000010100000100000 =
b101001000010100000100000 >
b101001000010100000100000 W
b101 <
b10100 6
b10100 E
b10100 d
b10100 h
b10100 *"
12
#75
02
#80
0D
0A
b0 s
b0 #"
1e
0B
0C
1M
b1 N
b1 Q
b1 T
1|
1v
b10 $"
b100001 U
b110 J
b110 O
b110 R
b110 V
b110 l
b1000 _
b1000 :"
b1000 ="
b11111111111111111111111111111100 p
b11111111111111111111111111111100 {
b11111111111111111111111111111100 q
b11111111111111111111111111111100 y
b11111111111111111111111111111100 }
b1000 1
b1000 8
b1000 :
b1000 I
b1000 f
b1000 u
b1000 %"
b1000 8"
b11 [
b11 i
b11 o
b11 z
b11100 b
b11100 g
b11100 7"
b11 /
b11 4
b11 9
b11 @
b11 Z
b11 k
b11 >"
b111 Y
b111 @"
b111 E"
b101000 ]
b101000 &"
b101000 ."
b1000 t
b1000 w
b1000 ""
b11111111111111111111111111111111 n
b11111111111111111111111111111111 !"
b1000 m
b1000 ~
b1000100 c
b1000100 0"
b1000100 3"
b11100 a
b11100 4"
b11100 5"
b100 L
b100 S
b1010 K
b1010 P
b10100111000000000000101000 6"
b111 <"
b111 C"
b0 D"
b1010 ^
b1010 j
b1010 '"
b1010 B"
b1010 A"
b1011 \
b1011 r
b1011 x
b1011 ?"
b11100 `
b11100 +"
b11100 /"
b11100 2"
b10000101001110000000000001010 7
b10000101001110000000000001010 =
b10000101001110000000000001010 >
b10000101001110000000000001010 W
b110 <
b11000 6
b11000 E
b11000 d
b11000 h
b11000 *"
12
#85
02
#90
1A
b11 $"
b111 J
b111 O
b111 R
b111 V
b111 l
1B
1C
0M
b10 N
b10 Q
b10 T
b110000010 U
b0 _
b0 :"
b0 ="
b0 1
b0 8
b0 :
b0 I
b0 f
b0 u
b0 %"
b0 8"
b11111111111111111111111111111000 q
b11111111111111111111111111111000 y
b11111111111111111111111111111000 }
b11111111111111111111111111111000 p
b11111111111111111111111111111000 {
b101 t
b101 w
b101 ""
b11111111111111111111111111111100 n
b11111111111111111111111111111100 !"
b1000 m
b1000 ~
b111 [
b111 i
b111 o
b111 z
b100000 b
b100000 g
b100000 7"
b1100 \
b1100 r
b1100 x
b1100 ?"
b111 /
b111 4
b111 9
b111 @
b111 Z
b111 k
b111 >"
b100 Y
b100 @"
b100 E"
b1000000010101000 ]
b1000000010101000 &"
b1000000010101000 ."
b1000000011001000 c
b1000000011001000 0"
b1000000011001000 3"
b100000 a
b100000 4"
b100000 5"
b0 L
b0 S
b101010 K
b101010 P
b1100100001000000010101000 6"
b11 ;"
b100 <"
b100 C"
b100 D"
b10000000101010 ^
b10000000101010 j
b10000000101010 '"
b10000000101010 B"
b10000000101010 A"
b100000 `
b100000 +"
b100000 /"
b100000 2"
b11001000010000000101010 7
b11001000010000000101010 =
b11001000010000000101010 >
b11001000010000000101010 W
b111 <
b11100 6
b11100 E
b11100 d
b11100 h
b11100 *"
12
#95
02
