Unpipelined/MIPS_core_tb.v
`timescale 1ns / 1ns
`include "MIPS_Single_Cycle.v"

module testbench;
    reg clk=0;
    reg reset=0;
    wire [31:0] writedata, dataadr;
    wire WE;
// instantiate device to be tested
    top dut (clk, reset, writedata, dataadr, WE);
// initialize test




    initial begin
        $dumpfile("top.vcd");
        $dumpvars;
    end



    initial
        begin
            reset <= 1; # 22; reset <=0;
        end
// generate clock to sequence tests
    initial
        for(integer i=0;i<1000;i++) begin
            clk <=1; # 5; clk <=0; # 5;
            
        end


// check results
    always @ (negedge clk)
        begin
            if (WE) begin
                if (dataadr === 84 & writedata === 7) begin
                    $display ("Simulation succeeded");
                    $stop;
                end else if (dataadr !==80) begin
                    $display ("Simulation failed");
                    $stop;
            end
        end
    end
endmodule

Unpipelined/MIPS_Single_Cycle.v
//on reset PC should begin at 0xBFC0 0000

module MIPS_Single_Cycle();

    initial begin

    end
endmodule


//32 bit flip flop with active high reset 
module Dflipflop(Q, clk, D, reset);

    input clk, reset; 
    input [31:0] D;
    output reg [31:0] Q;

    always @ (posedge clk)
        begin
            if(reset==1) Q<=0;

            Q<=D; //output new pc from alu on posedge clk 
        end
endmodule



//register file. Contains 32 internal registers. each 32 bits wide
//address 1 (A1) is read to RD1 asynchronously. Same is true for A2 and RD2.
//To write, input address is A3. Address to read is WD3. occurs on posedge clk
//write enable must also be active. 
module registerFile(RD1, RD2, A1, A2, A3, WD3, clk, WE3);
    
    output [31:0] RD1, RD2;  //outputs of the register file are each 32 bits since the regsiter is 32 bits wide
    input [4:0] A1,A2,A3;   //2^5=32 since 32 total addresses
    input [31:0] WD3; //the data to be written if WE3 is high 
    input clk, WE3; 

    reg [31:0] internal_mem [31:0]; //32 wires each 32 bits long

    
        always @ (posedge clk) 
            if (WE3==1) internal_mem[A3]<=WD3;
        
        assign RD1[0]=0;    //register 0 is always 0
        assign RD1=internal_mem[A1];
        assign RD2=internal_mem[A2];

endmodule


//in single cycle mips architecture, the program and variables are stored in
//two seperate registers. instruction memory stores the program, Data memory
//(TBD) stores variable information
module instruction_memory(RD, A);
    output [31:0] RD;    //output data is 32 bits wide because thats how long instructions are
    input [5:0] A;      //64 possible addresses

    reg [31:0] RAM [63:0]; //64 wires each 32 bits wide
    
    initial
        begin 
            $readmemh("memfile.dat",RAM); //read dissassembled MIPS code and load it into ram
    end

    assign RD = RAM[A]; //output onto bus. no need for clock because ram is asynchronous

endmodule




//more ram. This is where data is written during program exectuion. 
//writing is done on the clock, reading is done asynchronously
//input address is 32 bits, data width is 32 bits. 
module data_memory(RD,clk,A,WD,WE);
    //not using full memory capabilities
    //
    //
    //                                                                                                                      DOUBLE
    //                                                                                                                      CHECK
    //                                                                                                                      THIS
    //                                                                                                                      MODULE
    output [31:0] RD;
    input clk, WE;
    input [31:0] A,WD;


    reg [31:0] data [63:0];


    assign RD = data[A]; //address is always being read out

    always @ (posedge clk)
        if(WE==1) data[A] <=WD;
endmodule



module SignExtender(extend, extended);

    input [15:0] extend;
    output [31:0] extended;

    assign extended[31:0]= {{16{extend[15]}},extend[15:0]};

endmodule

module adder(Y, C_out, SrcA, SrcB);

    output [31:0] Y;
    output C_out;
    input [31:0] SrcA, SrcB;
    

    assign {C_out,Y}=SrcA+SrcB;


endmodule



//The input to the alu control logic depends on 2 things, the op code and the
//funct space (in R type instructions). For instance, an instruction with
//opcode 000000 is always going to have an AluOp of 10. 10 indicates that the
//ALUcontrol depends on the funct field of the instruction, (Or, Nor, Add all
//work differently). However, in I type instructions, there is no funct field,
//so the alu controll only depends on the opcode, and the logic for that is
//quite straight forward. 

//ALU decoder controls the operation that occurs in the alu
module AluDecoder(AluControl, AluOP, funct);

    output reg [2:0]AluControl;
    input [1:0] AluOP;
    input [5:0] funct;
    


    always @(*)
        if (AluOP==2'b0x) AluControl<=3'b010;
        else if (AluOP==2'bx1) AluControl <=3'b110;
        else if(AluOP==2'b1x) case(funct)
            6'b100000 : AluControl <= 3'b010;   //add
            6'b100010 : AluControl <= 3'b110;   //sub
            6'b100100 : AluControl <= 3'b000;   //and
            6'b100101 : AluControl <= 3'b001;   //or
            6'b101010 : AluControl <= 3'b011;   //slt
        default: AluControl <=3'bxxx;   //illegal opcode
        endcase
endmodule


module Or(Y, SrcA,SrcB);

    output [31:0] Y;
    input [31:0] SrcA, SrcB;


    assign Y=SrcA | SrcB;

endmodule

module And(Y, SrcA,SrcB);

    output [31:0] Y;
    input [31:0] SrcA, SrcB;


    assign Y=SrcA & SrcB;

endmodule
//subtract and add are done the same exact way. the only difference is that 
//subtract is compiled as the addition of a twos complement number to
//a posative 
module ALU(Zero, ALUResult, C_out, ALUControl, SrcA, SrcB);

    output reg Zero;
    output [31:0] ALUResult;
    output C_out;
    input [2:0] ALUControl;
    input [31:0] SrcA, SrcB;
    
    wire [31:0] SrcB_not; assign SrcB_not=~SrcB;
    wire [31:0] mux1_out;
    wire [31:0] N0,N1,N2,N3;


    mux_2_32b mux1(mux1_out,ALUControl[2], SrcB,SrcB_not);
 
    assign N0=mux1_out&SrcA;

    assign N1=mux1_out&SrcA;


    adder add1(N2,C_out,mux1_out,SrcA);
    assign N3={1'b0,N2[30:0]};

    mux_4_32b mux2(ALUResult,ALUControl[1:0],N0,N1,N2,N3);

    always @(*)
        if (ALUResult==0) Zero=1;
        else Zero=0;

endmodule








module shift_left_2(shifted_out,shift_in);

    input [31:0] shift_in;
    output [31:0] shifted_out;


    assign shifted_out=shift_in<<2;
endmodule


module mux_2_32b(out, sel, D0, D1);

    output [31:0] out;
    input sel;
    input [31:0] D0, D1;
    
    assign out=sel? D1:D0;

endmodule


module mux_4_32b(out, sel, D0, D1, D2, D3);

    output [31:0] out;
    input [1:0]sel;
    input [31:0] D0, D1, D2, D3;
    
    assign out=sel[1]? (sel[0]?D3:D2):(sel[0]? D1: D0);

endmodule




//The main decoder for the system. Seperate from ALU decoder. This can be
//viewed as the microcode of the system for each instruction. 
module mainDecoder(MemWrite, RegWrite, RegDst, ALUSrc, MemtoReg, Branch, ALUOp, Jump, Opcode);
    output MemWrite, RegWrite, RegDst, ALUSrc, MemtoReg, Branch, Jump;
    output [1:0] ALUOp;
    input [5:0] Opcode;

    reg [8:0] controls;

    assign {RegWrite,RegDst,ALUSrc,Branch,MemWrite,MemtoReg,ALUOp,Jump}=controls;
    always @(*)
        if(Opcode==6'b000000) assign controls=9'b110000100;
        else if(Opcode==6'b100011) assign controls=9'b101001000;           
        else if (Opcode==6'b101011) assign controls=9'b0x101x000;
        else if (Opcode==6'b000100) assign controls=9'b0x010x010;
        else if (Opcode==6'b001000) assign controls=9'b101000000;
        else if (Opcode==6'b000010) assign controls=9'b0xxx0xxx1;
        else assign controls=9'bxxxxxxxxx;
endmodule


module controller (ALUControl, PCSrc, MemtoReg,ALUSrc,RegDst,RegWrite, MemWrite, Opcode, Funct, Zero, Jump);

    
    output [2:0] ALUControl;
    output PCSrc, MemtoReg, ALUSrc, RegDst, RegWrite, MemWrite,Jump;

    input [5:0] Funct;
    input [5:0] Opcode;
    input Zero;
    
    wire Branch;
    wire [1:0] ALUOp;

    mainDecoder md1(MemWrite, RegWrite, RegDst, ALUSrc, MemtoReg, Branch, ALUOp, Jump, Opcode);

    AluDecoder aludec1(ALUControl, ALUOp,Funct);

    assign PCSrc=Branch & Zero; //source of pc.


endmodule



module datapath(ALUOut, WriteData, PC, Zero, Reset, Clk, ALUControl, PCSrc, MemtoReg, ALUSrc, RegDst, RegWrite, Jump, ReadData,Instr);

    output Zero; //zero flag if alu output is 0
    output [31:0] PC; //program counter output after selection (final PC for instruction retrieving)
    output [31:0] ALUOut, WriteData;
    
    input Reset, Clk, MemtoReg, PCSrc, ALUSrc, RegDst, RegWrite, Jump;
    input [2:0] ALUControl; 
    input [31:0] ReadData; //inputs datat to datapath
    input [31:0] Instr;

    wire [4:0] RegisterAddress; //address if writing to registers (A3)
    
    
    wire [31:0] PCNext, PCNextbr, PCPlus4, PCBranch; 
    //PCPLUS4 is the output of the ALU after adding 4
    //PCBranch is the PC value after a branch instruction (which uses relative addressing)
    //PCNextbr is the output of the mux after selecting between branching and just adding 4
    
    //PCNext is the value of the PC that is stored in the PC regitser

    wire [31:0] SignImm, SignImmSh;
    //a branch may be posative or negative. Since the PC is 32 bits and the
    //largest possible relative address is 16 bits, it must be extended to 32
    //bits with the correct sign in mind. 
    //SignImm is the unextended branch value (relative address) and SignImmSh
    //is the sign extended relative address inputted to the PC ALU

    wire [31:0] SrcA, SrcB; 
    //inputs to the main ALU

    wire [31:0] Result;
    //This is not the alu resut, it is the output of the mux that selects
    //between data memory outout and aluoutput. This is imporatnt as it
    //determines what is written to the register file
    

    Dflipflop PCRegister(PC,Clk, PCNext, Reset);
    //PCRegister


    adder pcadd1(PCPlus4,,32'b100,PC); //the adder for the Program counter iteration

    shift_left_2 immsh(SignImmSh,SignImm);
    //shiftng for branch operatioms (multiply by 4)

    adder pcadd2 (PCBranch,,SignImmSh,PCPlus4);
    //the adder for branch operations. number of bytes+PC
    
    mux_2_32b pcbrmux(PCNextbr,PCSrc, PCPlus4, PCBranch);
    //this mux determines if the pc should use the next address(PC+4) or the
    //branched PC (PCBranch) address based on contrrol logic from main dec

    mux_2_32b pcmux(PCNext, Jump,PCNextbr, {PCPlus4[31:28],Instr[25:0], 2'b00});



    


    //register file 
    

    registerFile rf(SrcA, WriteData,Instr[25:21],Instr[20:16],RegisterAddress,WriteData,Clk, RegWrite);

    mux_2_5b A3Mux(RegisterAddress,RegDst,Instr[20:16],Instr[25:21]);

    mux_2_32b WD3Mux(Result,MemtoReg,ALUOut, ReadData);

    SignExtender se(Instr[15:0],SignImm);
    //ALU
    mux_2_32b SRCBmux (SrcB, ALUSrc, WriteData, SignImm);
    
    ALU alu_main (Zero, ALUOut, , ALUControl,SrcA, SrcB);




endmodule

module mux_2_5b(out, sel, D0, D1); //for controlling A3

    output [4:0] out;
    input sel;
    input [4:0] D0, D1;
    
    assign out=sel? D1:D0;

endmodule


module MIPS (ALUOut,WriteData,WE, PC,Instr,ReadData,Reset,Clk);

    output  WE; //write enable
    output [31:0] ALUOut,WriteData;
    output [31:0] PC;
    input [31:0] Instr, ReadData;
    input Reset,Clk;

    wire MemToReg, Branch,ALUSrc, RegDst, RegWrite, Jump,PCSrc,Zero;
    wire [2:0] ALUControl;
    
    controller control(ALUControl,PCSrc,MemToReg,ALUSrc,RegDst,RegWrite,WE,Instr[31:26],Instr[5:0],Zero,Jump);


    datapath dp(ALUOut, WriteData, PC, Zero, Reset, Clk, ALUControl, PCSrc, MemToReg, ALUSrc, RegDst, RegWrite, Jump, ReadData,Instr);


endmodule


module top(Clk, Reset, WriteData,DataAdr,WE);

    input Clk, Reset;
    output [31:0] WriteData, DataAdr;
    output WE;


    wire [31:0] PC, Instr, ReadData;


    MIPS mips(DataAdr,WriteData,WE, PC,Instr,ReadData,Reset,Clk);


    instruction_memory imem(Instr,PC[7:2]);

    data_memory dmem(ReadData, Clk, DataAdr, WriteData, WE);

endmodule

Unpipelined/top.vcd
$date
	Wed Jun  1 20:48:59 2022
$end
$version
	Icarus Verilog
$end
$timescale
	1ns
$end
$scope module And $end
$var wire 32 ! SrcA [31:0] $end
$var wire 32 " SrcB [31:0] $end
$var wire 32 # Y [31:0] $end
$upscope $end
$scope module MIPS_Single_Cycle $end
$upscope $end
$scope module Or $end
$var wire 32 $ SrcA [31:0] $end
$var wire 32 % SrcB [31:0] $end
$var wire 32 & Y [31:0] $end
$upscope $end
$scope module testbench $end
$var wire 32 ' writedata [31:0] $end
$var wire 32 ( dataadr [31:0] $end
$var wire 1 ) WE $end
$var reg 1 * clk $end
$var reg 1 + reset $end
$scope module dut $end
$var wire 1 * Clk $end
$var wire 1 + Reset $end
$var wire 32 , WriteData [31:0] $end
$var wire 1 ) WE $end
$var wire 32 - ReadData [31:0] $end
$var wire 32 . PC [31:0] $end
$var wire 32 / Instr [31:0] $end
$var wire 32 0 DataAdr [31:0] $end
$scope module dmem $end
$var wire 32 1 RD [31:0] $end
$var wire 1 * clk $end
$var wire 1 ) WE $end
$var wire 32 2 WD [31:0] $end
$var wire 32 3 A [31:0] $end
$upscope $end
$scope module imem $end
$var wire 6 4 A [5:0] $end
$var wire 32 5 RD [31:0] $end
$upscope $end
$scope module mips $end
$var wire 1 * Clk $end
$var wire 32 6 Instr [31:0] $end
$var wire 32 7 ReadData [31:0] $end
$var wire 1 + Reset $end
$var wire 1 8 Zero $end
$var wire 32 9 WriteData [31:0] $end
$var wire 1 ) WE $end
$var wire 1 : RegWrite $end
$var wire 1 ; RegDst $end
$var wire 1 < PCSrc $end
$var wire 32 = PC [31:0] $end
$var wire 1 > MemToReg $end
$var wire 1 ? Jump $end
$var wire 1 @ ALUSrc $end
$var wire 32 A ALUOut [31:0] $end
$var wire 3 B ALUControl [2:0] $end
$scope module control $end
$var wire 6 C Funct [5:0] $end
$var wire 6 D Opcode [5:0] $end
$var wire 1 < PCSrc $end
$var wire 1 8 Zero $end
$var wire 1 : RegWrite $end
$var wire 1 ; RegDst $end
$var wire 1 > MemtoReg $end
$var wire 1 ) MemWrite $end
$var wire 1 ? Jump $end
$var wire 1 E Branch $end
$var wire 1 @ ALUSrc $end
$var wire 2 F ALUOp [1:0] $end
$var wire 3 G ALUControl [2:0] $end
$scope module aludec1 $end
$var wire 6 H funct [5:0] $end
$var wire 2 I AluOP [1:0] $end
$var reg 3 J AluControl [2:0] $end
$upscope $end
$scope module md1 $end
$var wire 6 K Opcode [5:0] $end
$var wire 1 : RegWrite $end
$var wire 1 ; RegDst $end
$var wire 1 > MemtoReg $end
$var wire 1 ) MemWrite $end
$var wire 1 ? Jump $end
$var wire 1 E Branch $end
$var wire 1 @ ALUSrc $end
$var wire 2 L ALUOp [1:0] $end
$var reg 9 M controls [8:0] $end
$upscope $end
$upscope $end
$scope module dp $end
$var wire 3 N ALUControl [2:0] $end
$var wire 1 @ ALUSrc $end
$var wire 1 * Clk $end
$var wire 32 O Instr [31:0] $end
$var wire 1 ? Jump $end
$var wire 1 > MemtoReg $end
$var wire 1 < PCSrc $end
$var wire 32 P ReadData [31:0] $end
$var wire 1 ; RegDst $end
$var wire 1 : RegWrite $end
$var wire 1 + Reset $end
$var wire 32 Q SrcA [31:0] $end
$var wire 1 8 Zero $end
$var wire 32 R WriteData [31:0] $end
$var wire 32 S SrcB [31:0] $end
$var wire 32 T SignImmSh [31:0] $end
$var wire 32 U SignImm [31:0] $end
$var wire 32 V Result [31:0] $end
$var wire 5 W RegisterAddress [4:0] $end
$var wire 32 X PCPlus4 [31:0] $end
$var wire 32 Y PCNextbr [31:0] $end
$var wire 32 Z PCNext [31:0] $end
$var wire 32 [ PCBranch [31:0] $end
$var wire 32 \ PC [31:0] $end
$var wire 32 ] ALUOut [31:0] $end
$scope module A3Mux $end
$var wire 5 ^ D0 [4:0] $end
$var wire 5 _ D1 [4:0] $end
$var wire 1 ; sel $end
$var wire 5 ` out [4:0] $end
$upscope $end
$scope module PCRegister $end
$var wire 1 * clk $end
$var wire 1 + reset $end
$var wire 32 a D [31:0] $end
$var reg 32 b Q [31:0] $end
$upscope $end
$scope module SRCBmux $end
$var wire 1 @ sel $end
$var wire 32 c out [31:0] $end
$var wire 32 d D1 [31:0] $end
$var wire 32 e D0 [31:0] $end
$upscope $end
$scope module WD3Mux $end
$var wire 32 f D1 [31:0] $end
$var wire 1 > sel $end
$var wire 32 g out [31:0] $end
$var wire 32 h D0 [31:0] $end
$upscope $end
$scope module alu_main $end
$var wire 3 i ALUControl [2:0] $end
$var wire 32 j N0 [31:0] $end
$var wire 32 k N1 [31:0] $end
$var wire 32 l SrcA [31:0] $end
$var wire 32 m SrcB [31:0] $end
$var wire 32 n SrcB_not [31:0] $end
$var wire 32 o mux1_out [31:0] $end
$var wire 32 p N3 [31:0] $end
$var wire 32 q N2 [31:0] $end
$var wire 1 r C_out $end
$var wire 32 s ALUResult [31:0] $end
$var reg 1 8 Zero $end
$scope module add1 $end
$var wire 32 t SrcB [31:0] $end
$var wire 32 u Y [31:0] $end
$var wire 32 v SrcA [31:0] $end
$var wire 1 r C_out $end
$upscope $end
$scope module mux1 $end
$var wire 32 w D0 [31:0] $end
$var wire 32 x D1 [31:0] $end
$var wire 1 y sel $end
$var wire 32 z out [31:0] $end
$upscope $end
$scope module mux2 $end
$var wire 32 { D0 [31:0] $end
$var wire 32 | D1 [31:0] $end
$var wire 32 } D2 [31:0] $end
$var wire 32 ~ D3 [31:0] $end
$var wire 2 !" sel [1:0] $end
$var wire 32 "" out [31:0] $end
$upscope $end
$upscope $end
$scope module immsh $end
$var wire 32 #" shifted_out [31:0] $end
$var wire 32 $" shift_in [31:0] $end
$upscope $end
$scope module pcadd1 $end
$var wire 32 %" SrcA [31:0] $end
$var wire 32 &" SrcB [31:0] $end
$var wire 32 '" Y [31:0] $end
$var wire 1 (" C_out $end
$upscope $end
$scope module pcadd2 $end
$var wire 32 )" SrcA [31:0] $end
$var wire 32 *" SrcB [31:0] $end
$var wire 32 +" Y [31:0] $end
$var wire 1 ," C_out $end
$upscope $end
$scope module pcbrmux $end
$var wire 32 -" D0 [31:0] $end
$var wire 32 ." D1 [31:0] $end
$var wire 1 < sel $end
$var wire 32 /" out [31:0] $end
$upscope $end
$scope module pcmux $end
$var wire 32 0" D0 [31:0] $end
$var wire 32 1" D1 [31:0] $end
$var wire 1 ? sel $end
$var wire 32 2" out [31:0] $end
$upscope $end
$scope module rf $end
$var wire 5 3" A1 [4:0] $end
$var wire 5 4" A2 [4:0] $end
$var wire 5 5" A3 [4:0] $end
$var wire 32 6" RD1 [31:0] $end
$var wire 32 7" RD2 [31:0] $end
$var wire 32 8" WD3 [31:0] $end
$var wire 1 : WE3 $end
$var wire 1 * clk $end
$upscope $end
$scope module se $end
$var wire 16 9" extend [15:0] $end
$var wire 32 :" extended [31:0] $end
$upscope $end
$upscope $end
$upscope $end
$upscope $end
$scope begin $ivl_for_loop0 $end
$var integer 32 ;" i [31:0] $end
$upscope $end
$upscope $end
$enddefinitions $end
#0
$dumpvars
b0 ;"
bx :"
bx 9"
bx 8"
bx 7"
bx 6"
bx 5"
bx 4"
bx 3"
bx 2"
bx00 1"
bx 0"
bx /"
bx ."
bx -"
x,"
bx +"
bx *"
bx00 )"
x("
bx '"
bx &"
b100 %"
bx $"
bx00 #"
bx ""
bx !"
b0xxxxxxxxxxxxxxxxxxxxxxxxxxxxxxx ~
bx }
bx |
bx {
bx z
xy
bx x
bx w
bx v
bx u
bx t
bx s
xr
bx q
b0xxxxxxxxxxxxxxxxxxxxxxxxxxxxxxx p
bx o
bx n
bx m
bx l
bx k
bx j
bx i
bx h
bx g
bx f
bx e
bx d
bx c
bx b
bx a
bx `
bx _
bx ^
bx ]
bx \
bx [
bx Z
bx Y
bx X
bx W
bx V
bx U
bx00 T
bx S
bx R
bx Q
bx P
bx O
bx N
bx M
bx L
bx K
bx J
bx I
bx H
bx G
bx F
xE
bx D
bx C
bx B
bx A
x@
x?
x>
bx =
x<
x;
x:
bx 9
x8
bx 7
bx 6
bx 5
bx 4
bx 3
bx 2
bx 1
bx 0
bx /
bx .
bx -
bx ,
1+
1*
x)
bx (
bx '
bx &
bz %
bz $
bx #
bz "
bz !
$end
#5
0*
#10
bx .
bx =
bx \
bx b
bx &"
1*
b1 ;"
#15
0*
#20
bx .
bx =
bx \
bx b
bx &"
1*
b10 ;"
#22
0+
#25
0*
#30
1*
b11 ;"
#35
0*
#40
1*
b100 ;"
#45
0*
#50
1*
b101 ;"
#55
0*
#60
1*
b110 ;"
#65
0*
#70
1*
b111 ;"
#75
0*
#80
1*
b1000 ;"
#85
0*
#90
1*
b1001 ;"
#95
0*
#100
1*
b1010 ;"
#105
0*
#110
1*
b1011 ;"
#115
0*
#120
1*
b1100 ;"
#125
0*
#130
1*
b1101 ;"
#135
0*
#140
1*
b1110 ;"
#145
0*
#150
1*
b1111 ;"
#155
0*
#160
1*
b10000 ;"
#165
0*
#170
1*
b10001 ;"
#175
0*
#180
1*
b10010 ;"
#185
0*
#190
1*
b10011 ;"
#195
0*
#200
1*
b10100 ;"
#205
0*
#210
1*
b10101 ;"
#215
0*
#220
1*
b10110 ;"
#225
0*
#230
1*
b10111 ;"
#235
0*
#240
1*
b11000 ;"
#245
0*
#250
1*
b11001 ;"
#255
0*
#260
1*
b11010 ;"
#265
0*
#270
1*
b11011 ;"
#275
0*
#280
1*
b11100 ;"
#285
0*
#290
1*
b11101 ;"
#295
0*
#300
1*
b11110 ;"
#305
0*
#310
1*
b11111 ;"
#315
0*
#320
1*
b100000 ;"
#325
0*
#330
1*
b100001 ;"
#335
0*
#340
1*
b100010 ;"
#345
0*
#350
1*
b100011 ;"
#355
0*
#360
1*
b100100 ;"
#365
0*
#370
1*
b100101 ;"
#375
0*
#380
1*
b100110 ;"
#385
0*
#390
1*
b100111 ;"
#395
0*
#400
1*
b101000 ;"
#405
0*
#410
1*
b101001 ;"
#415
0*
#420
1*
b101010 ;"
#425
0*
#430
1*
b101011 ;"
#435
0*
#440
1*
b101100 ;"
#445
0*
#450
1*
b101101 ;"
#455
0*
#460
1*
b101110 ;"
#465
0*
#470
1*
b101111 ;"
#475
0*
#480
1*
b110000 ;"
#485
0*
#490
1*
b110001 ;"
#495
0*
#500
1*
b110010 ;"
#505
0*
#510
1*
b110011 ;"
#515
0*
#520
1*
b110100 ;"
#525
0*
#530
1*
b110101 ;"
#535
0*
#540
1*
b110110 ;"
#545
0*
#550
1*
b110111 ;"
#555
0*
#560
1*
b111000 ;"
#565
0*
#570
1*
b111001 ;"
#575
0*
#580
1*
b111010 ;"
#585
0*
#590
1*
b111011 ;"
#595
0*
#600
1*
b111100 ;"
#605
0*
#610
1*
b111101 ;"
#615
0*
#620
1*
b111110 ;"
#625
0*
#630
1*
b111111 ;"
#635
0*
#640
1*
b1000000 ;"
#645
0*
#650
1*
b1000001 ;"
#655
0*
#660
1*
b1000010 ;"
#665
0*
#670
1*
b1000011 ;"
#675
0*
#680
1*
b1000100 ;"
#685
0*
#690
1*
b1000101 ;"
#695
0*
#700
1*
b1000110 ;"
#705
0*
#710
1*
b1000111 ;"
#715
0*
#720
1*
b1001000 ;"
#725
0*
#730
1*
b1001001 ;"
#735
0*
#740
1*
b1001010 ;"
#745
0*
#750
1*
b1001011 ;"
#755
0*
#760
1*
b1001100 ;"
#765
0*
#770
1*
b1001101 ;"
#775
0*
#780
1*
b1001110 ;"
#785
0*
#790
1*
b1001111 ;"
#795
0*
#800
1*
b1010000 ;"
#805
0*
#810
1*
b1010001 ;"
#815
0*
#820
1*
b1010010 ;"
#825
0*
#830
1*
b1010011 ;"
#835
0*
#840
1*
b1010100 ;"
#845
0*
#850
1*
b1010101 ;"
#855
0*
#860
1*
b1010110 ;"
#865
0*
#870
1*
b1010111 ;"
#875
0*
#880
1*
b1011000 ;"
#885
0*
#890
1*
b1011001 ;"
#895
0*
#900
1*
b1011010 ;"
#905
0*
#910
1*
b1011011 ;"
#915
0*
#920
1*
b1011100 ;"
#925
0*
#930
1*
b1011101 ;"
#935
0*
#940
1*
b1011110 ;"
#945
0*
#950
1*
b1011111 ;"
#955
0*
#960
1*
b1100000 ;"
#965
0*
#970
1*
b1100001 ;"
#975
0*
#980
1*
b1100010 ;"
#985
0*
#990
1*
b1100011 ;"
#995
0*
#1000
1*
b1100100 ;"
#1005
0*
#1010
1*
b1100101 ;"
#1015
0*
#1020
1*
b1100110 ;"
#1025
0*
#1030
1*
b1100111 ;"
#1035
0*
#1040
1*
b1101000 ;"
#1045
0*
#1050
1*
b1101001 ;"
#1055
0*
#1060
1*
b1101010 ;"
#1065
0*
#1070
1*
b1101011 ;"
#1075
0*
#1080
1*
b1101100 ;"
#1085
0*
#1090
1*
b1101101 ;"
#1095
0*
#1100
1*
b1101110 ;"
#1105
0*
#1110
1*
b1101111 ;"
#1115
0*
#1120
1*
b1110000 ;"
#1125
0*
#1130
1*
b1110001 ;"
#1135
0*
#1140
1*
b1110010 ;"
#1145
0*
#1150
1*
b1110011 ;"
#1155
0*
#1160
1*
b1110100 ;"
#1165
0*
#1170
1*
b1110101 ;"
#1175
0*
#1180
1*
b1110110 ;"
#1185
0*
#1190
1*
b1110111 ;"
#1195
0*
#1200
1*
b1111000 ;"
#1205
0*
#1210
1*
b1111001 ;"
#1215
0*
#1220
1*
b1111010 ;"
#1225
0*
#1230
1*
b1111011 ;"
#1235
0*
#1240
1*
b1111100 ;"
#1245
0*
#1250
1*
b1111101 ;"
#1255
0*
#1260
1*
b1111110 ;"
#1265
0*
#1270
1*
b1111111 ;"
#1275
0*
#1280
1*
b10000000 ;"
#1285
0*
#1290
1*
b10000001 ;"
#1295
0*
#1300
1*
b10000010 ;"
#1305
0*
#1310
1*
b10000011 ;"
#1315
0*
#1320
1*
b10000100 ;"
#1325
0*
#1330
1*
b10000101 ;"
#1335
0*
#1340
1*
b10000110 ;"
#1345
0*
#1350
1*
b10000111 ;"
#1355
0*
#1360
1*
b10001000 ;"
#1365
0*
#1370
1*
b10001001 ;"
#1375
0*
#1380
1*
b10001010 ;"
#1385
0*
#1390
1*
b10001011 ;"
#1395
0*
#1400
1*
b10001100 ;"
#1405
0*
#1410
1*
b10001101 ;"
#1415
0*
#1420
1*
b10001110 ;"
#1425
0*
#1430
1*
b10001111 ;"
#1435
0*
#1440
1*
b10010000 ;"
#1445
0*
#1450
1*
b10010001 ;"
#1455
0*
#1460
1*
b10010010 ;"
#1465
0*
#1470
1*
b10010011 ;"
#1475
0*
#1480
1*
b10010100 ;"
#1485
0*
#1490
1*
b10010101 ;"
#1495
0*
#1500
1*
b10010110 ;"
#1505
0*
#1510
1*
b10010111 ;"
#1515
0*
#1520
1*
b10011000 ;"
#1525
0*
#1530
1*
b10011001 ;"
#1535
0*
#1540
1*
b10011010 ;"
#1545
0*
#1550
1*
b10011011 ;"
#1555
0*
#1560
1*
b10011100 ;"
#1565
0*
#1570
1*
b10011101 ;"
#1575
0*
#1580
1*
b10011110 ;"
#1585
0*
#1590
1*
b10011111 ;"
#1595
0*
#1600
1*
b10100000 ;"
#1605
0*
#1610
1*
b10100001 ;"
#1615
0*
#1620
1*
b10100010 ;"
#1625
0*
#1630
1*
b10100011 ;"
#1635
0*
#1640
1*
b10100100 ;"
#1645
0*
#1650
1*
b10100101 ;"
#1655
0*
#1660
1*
b10100110 ;"
#1665
0*
#1670
1*
b10100111 ;"
#1675
0*
#1680
1*
b10101000 ;"
#1685
0*
#1690
1*
b10101001 ;"
#1695
0*
#1700
1*
b10101010 ;"
#1705
0*
#1710
1*
b10101011 ;"
#1715
0*
#1720
1*
b10101100 ;"
#1725
0*
#1730
1*
b10101101 ;"
#1735
0*
#1740
1*
b10101110 ;"
#1745
0*
#1750
1*
b10101111 ;"
#1755
0*
#1760
1*
b10110000 ;"
#1765
0*
#1770
1*
b10110001 ;"
#1775
0*
#1780
1*
b10110010 ;"
#1785
0*
#1790
1*
b10110011 ;"
#1795
0*
#1800
1*
b10110100 ;"
#1805
0*
#1810
1*
b10110101 ;"
#1815
0*
#1820
1*
b10110110 ;"
#1825
0*
#1830
1*
b10110111 ;"
#1835
0*
#1840
1*
b10111000 ;"
#1845
0*
#1850
1*
b10111001 ;"
#1855
0*
#1860
1*
b10111010 ;"
#1865
0*
#1870
1*
b10111011 ;"
#1875
0*
#1880
1*
b10111100 ;"
#1885
0*
#1890
1*
b10111101 ;"
#1895
0*
#1900
1*
b10111110 ;"
#1905
0*
#1910
1*
b10111111 ;"
#1915
0*
#1920
1*
b11000000 ;"
#1925
0*
#1930
1*
b11000001 ;"
#1935
0*
#1940
1*
b11000010 ;"
#1945
0*
#1950
1*
b11000011 ;"
#1955
0*
#1960
1*
b11000100 ;"
#1965
0*
#1970
1*
b11000101 ;"
#1975
0*
#1980
1*
b11000110 ;"
#1985
0*
#1990
1*
b11000111 ;"
#1995
0*
#2000
1*
b11001000 ;"
#2005
0*
#2010
1*
b11001001 ;"
#2015
0*
#2020
1*
b11001010 ;"
#2025
0*
#2030
1*
b11001011 ;"
#2035
0*
#2040
1*
b11001100 ;"
#2045
0*
#2050
1*
b11001101 ;"
#2055
0*
#2060
1*
b11001110 ;"
#2065
0*
#2070
1*
b11001111 ;"
#2075
0*
#2080
1*
b11010000 ;"
#2085
0*
#2090
1*
b11010001 ;"
#2095
0*
#2100
1*
b11010010 ;"
#2105
0*
#2110
1*
b11010011 ;"
#2115
0*
#2120
1*
b11010100 ;"
#2125
0*
#2130
1*
b11010101 ;"
#2135
0*
#2140
1*
b11010110 ;"
#2145
0*
#2150
1*
b11010111 ;"
#2155
0*
#2160
1*
b11011000 ;"
#2165
0*
#2170
1*
b11011001 ;"
#2175
0*
#2180
1*
b11011010 ;"
#2185
0*
#2190
1*
b11011011 ;"
#2195
0*
#2200
1*
b11011100 ;"
#2205
0*
#2210
1*
b11011101 ;"
#2215
0*
#2220
1*
b11011110 ;"
#2225
0*
#2230
1*
b11011111 ;"
#2235
0*
#2240
1*
b11100000 ;"
#2245
0*
#2250
1*
b11100001 ;"
#2255
0*
#2260
1*
b11100010 ;"
#2265
0*
#2270
1*
b11100011 ;"
#2275
0*
#2280
1*
b11100100 ;"
#2285
0*
#2290
1*
b11100101 ;"
#2295
0*
#2300
1*
b11100110 ;"
#2305
0*
#2310
1*
b11100111 ;"
#2315
0*
#2320
1*
b11101000 ;"
#2325
0*
#2330
1*
b11101001 ;"
#2335
0*
#2340
1*
b11101010 ;"
#2345
0*
#2350
1*
b11101011 ;"
#2355
0*
#2360
1*
b11101100 ;"
#2365
0*
#2370
1*
b11101101 ;"
#2375
0*
#2380
1*
b11101110 ;"
#2385
0*
#2390
1*
b11101111 ;"
