Unpipelined/MIPS_core_tb.v
`timescale 1ns / 1ns
`include "MIPS_Single_Cycle.v"

module testbench;
    reg clk=0;
    reg reset=0;
    wire [31:0] writedata, dataadr;
    wire WE;
// instantiate device to be tested
    top dut (clk, reset, writedata, dataadr, WE);
// initialize test




    initial begin
        $dumpfile("top.vcd");
        $dumpvars;
    end






    initial
        begin
            reset <= 1; # 22; reset <=0;
        end


// generate clock to sequence tests
    always begin
            clk <=1; # 5; clk <=0; # 5;
            
        end


// check results
    always @ (negedge clk)
        begin
            if (WE) begin
                if (dataadr === 84 & writedata === 7) begin
                    $display ("Simulation succeeded");
                    $stop;
                end else if (dataadr !==80) begin
                    $display ("Simulation failed");
                    $stop;
            end
        end
    end
endmodule

Unpipelined/MIPS_Single_Cycle.v
//on reset PC should begin at 0xBFC0 0000



//32 bit flip flop with active high reset 
module Dflipflop(Q, clk, D, reset);

    input clk, reset; 
    input [31:0] D;
    output reg [31:0] Q;

    always @ (posedge clk,posedge reset)
        if(reset==1) Q<=0;
        else Q<=D; //output new pc from alu on posedge clk 
endmodule



//register file. Contains 32 internal registers. each 32 bits wide
//address 1 (A1) is read to RD1 asynchronously. Same is true for A2 and RD2.
//To write, input address is A3. Address to read is WD3. occurs on posedge clk
//write enable must also be active. 
module registerFile(RD1, RD2, A1, A2, A3, WD3, clk, WE3);
    
    output [31:0] RD1, RD2;  //outputs of the register file are each 32 bits since the regsiter is 32 bits wide
    input [4:0] A1,A2,A3;   //2^5=32 since 32 total addresses
    input [31:0] WD3; //the data to be written if WE3 is high 
    input clk, WE3; 

    reg [31:0] internal_mem [31:0]; //32 wires each 32 bits long

    
        always @ (posedge clk) 
            if (WE3==1) internal_mem[A3]<=WD3;
        

    assign RD1 = (A1 !=0) ? internal_mem[A1] :0;
    assign RD2 = (A2 !=0) ? internal_mem[A2] :0;

endmodule


//in single cycle mips architecture, the program and variables are stored in
//two seperate registers. instruction memory stores the program, Data memory
//(TBD) stores variable information
module instruction_memory(RD, A);
    output [31:0] RD;    //output data is 32 bits wide because thats how long instructions are
    input [5:0] A;      //64 possible addresses

    reg [31:0] RAM [63:0]; //64 wires each 32 bits wide
    
    initial
        begin 
            $readmemh("memfile.dat",RAM); //read dissassembled MIPS code and load it into ram
    end

    assign RD = RAM[A]; //output onto bus. no need for clock because ram is asynchronous

endmodule




//more ram. This is where data is written during program exectuion. 
//writing is done on the clock, reading is done asynchronously
//input address is 32 bits, data width is 32 bits. 
module data_memory(RD,clk,A,WD,WE);
    //not using full memory capabilities
    //
    //
    //                                                                                                                      DOUBLE
    //                                                                                                                      CHECK
    //                                                                                                                      THIS
    //                                                                                                                      MODULE
    output reg [31:0] RD;
    input clk, WE;
    input [31:0] A,WD;


    reg [31:0] data [63:0];


//    assign RD = data[A[31:2]]; //address is always being read out

  //  always @ (posedge clk)
    //    if(WE==1) data[A[31:2]] <=WD;

    always @(*) begin
       RD <= data[A]; //address is always being read out
    end


    always @ (posedge clk)
        if(WE==1) data[A[31:2]] <=WD;

endmodule



module SignExtender(extend, extended);

    input [15:0] extend;
    output [31:0] extended;

    assign extended[31:0]= {{16{extend[15]}},extend[15:0]};

endmodule

module adder(Y,C_out,C_in,SrcA, SrcB);

    output [31:0] Y;
    output C_out;
    input [31:0] SrcA, SrcB;
    input C_in;
    

    assign {C_out,Y}=SrcA+SrcB+C_in;


endmodule



//The input to the alu control logic depends on 2 things, the op code and the
//funct space (in R type instructions). For instance, an instruction with
//opcode 000000 is always going to have an AluOp of 10. 10 indicates that the
//ALUcontrol depends on the funct field of the instruction, (Or, Nor, Add all
//work differently). However, in I type instructions, there is no funct field,
//so the alu controll only depends on the opcode, and the logic for that is
//quite straight forward. 

//ALU decoder controls the operation that occurs in the alu
module AluDecoder(AluControl, AluOP, funct);

    output reg [2:0]AluControl;
    input [1:0] AluOP;
    input [5:0] funct;
    

    always @ (*)
        case (AluOP)
            2'b00: AluControl <=3'b010;
            2'b01: AluControl <=3'b110;
            default: case(funct)
                6'b100000 : AluControl <= 3'b010;   //add
                6'b100010 : AluControl <= 3'b110;   //sub
                6'b100100 : AluControl <= 3'b000;   //and
                6'b100101 : AluControl <= 3'b001;   //or
                6'b101010 : AluControl <= 3'b111;   //slt
                default: AluControl <=3'bxxx;
            endcase
        endcase
endmodule
/*

    always @(*)
        if (AluOP==2'b0x) AluControl<=3'b010;
        else if (AluOP==2'bx1) AluControl <=3'b110;
        else if(AluOP==2'b1x) case(funct)
            6'b100000 : AluControl <= 3'b010;   //add
            6'b100010 : AluControl <= 3'b110;   //sub
            6'b100100 : AluControl <= 3'b000;   //and
            6'b100101 : AluControl <= 3'b001;   //or
            6'b101010 : AluControl <= 3'b111;   //slt
        default: AluControl <=3'bxxx;   //illegal opcode
        endcase
endmodule
*/

module Or(Y, SrcA,SrcB);

    output [31:0] Y;
    input [31:0] SrcA, SrcB;


    assign Y=SrcA | SrcB;

endmodule

module And(Y, SrcA,SrcB);

    output [31:0] Y;
    input [31:0] SrcA, SrcB;


    assign Y=SrcA & SrcB;

endmodule
//subtract and add are done the same exact way. the only difference is that 
//subtract is compiled as the addition of a twos complement number to
//a posative 
module ALU(Zero, ALUResult, C_out, ALUControl, SrcA, SrcB);

    output Zero;
    output [31:0] ALUResult;
    output C_out;
    input [2:0] ALUControl;
    input [31:0] SrcA, SrcB;
    
    wire [31:0] SrcB_not; assign SrcB_not=~SrcB;
    wire [31:0] mux1_out;
    wire [31:0] N0,N1,N2,N3;


    mux_2_32b mux1(mux1_out,ALUControl[2], SrcB,SrcB_not);
 
    assign N0=mux1_out&SrcA;

    assign N1=mux1_out&SrcA;


    adder add1(N2,C_out,ALUControl[2],mux1_out,SrcA);
    assign N3={1'b0,N2[30:0]};

    mux_4_32b mux2(ALUResult,ALUControl[1:0],N0,N1,N2,N3);


    assign Zero = (ALUResult==0) ?   1 :0;

endmodule








module shift_left_2(shifted_out,shift_in);

    input [31:0] shift_in;
    output [31:0] shifted_out;


    assign shifted_out=shift_in<<2;
endmodule


module mux_2_32b(out, sel, D0, D1);

    output [31:0] out;
    input sel;
    input [31:0] D0, D1;
    
    assign out=sel? D1:D0;

endmodule


module mux_4_32b(out, sel, D0, D1, D2, D3);

    output [31:0] out;
    input [1:0]sel;
    input [31:0] D0, D1, D2, D3;
    
    assign out=sel[1]? (sel[0]?D3:D2):(sel[0]? D1: D0);

endmodule




//The main decoder for the system. Seperate from ALU decoder. This can be
//viewed as the microcode of the system for each instruction. 
module mainDecoder(MemWrite, RegWrite, RegDst, ALUSrc, MemtoReg, Branch, ALUOp, Jump, Opcode);
    output MemWrite, RegWrite, RegDst, ALUSrc, MemtoReg, Branch, Jump;
    output [1:0] ALUOp;
    input [5:0] Opcode;

    reg [8:0] controls;


    assign {RegWrite,RegDst,ALUSrc,Branch,MemWrite,MemtoReg,ALUOp,Jump}=controls;

    always @(*)
        if(Opcode==6'b000000) controls<=9'b110000010;
        else if(Opcode==6'b100011) controls<=9'b101001000;           
        else if (Opcode==6'b101011) controls<=9'b001010000;
        else if (Opcode==6'b000100) controls<=9'b000100001;
        else if (Opcode==6'b001000) controls<=9'b101000000;
        else if (Opcode==6'b000010) controls<=9'b000000100;
        else controls<=9'bxxxxxxxxx;
endmodule




module controller (ALUControl, PCSrc, MemtoReg,ALUSrc,RegDst,RegWrite, MemWrite, Opcode, Funct, Zero, Jump);

    
    output [2:0] ALUControl;
    output PCSrc, MemtoReg, ALUSrc, RegDst, RegWrite, MemWrite,Jump;

    input [5:0] Funct;
    input [5:0] Opcode;
    input Zero;
    
    wire Branch;
    wire [1:0] ALUOp;

    mainDecoder md1(MemWrite, RegWrite, RegDst, ALUSrc, MemtoReg, Branch, ALUOp, Jump, Opcode);

    AluDecoder aludec1(ALUControl, ALUOp,Funct);

    
    assign PCSrc=Branch & Zero; //source of pc. /\


endmodule



module datapath(ALUOut, WriteData, PC, Zero, Reset, Clk, ALUControl, PCSrc, MemtoReg, ALUSrc, RegDst, RegWrite, Jump, ReadData,Instr);

    output Zero; //zero flag if alu output is 0
    output [31:0] PC; //program counter output after selection (final PC for instruction retrieving)
    output [31:0] ALUOut, WriteData;
    
    input Reset, Clk, MemtoReg, PCSrc, ALUSrc, RegDst, RegWrite, Jump;
    input [2:0] ALUControl; 
    input [31:0] ReadData; //inputs datat to datapath
    input [31:0] Instr;

    wire [4:0] RegisterAddress; //address if writing to registers (A3)
    
    
    wire [31:0] PCNext, PCNextbr, PCPlus4, PCBranch; 
    //PCPLUS4 is the output of the ALU after adding 4
    //PCBranch is the PC value after a branch instruction (which uses relative addressing)
    //PCNextbr is the output of the mux after selecting between branching and just adding 4
    
    //PCNext is the value of the PC that is stored in the PC regitser

    wire [31:0] SignImm, SignImmSh;
    //a branch may be posative or negative. Since the PC is 32 bits and the
    //largest possible relative address is 16 bits, it must be extended to 32
    //bits with the correct sign in mind. 
    //SignImm is the unextended branch value (relative address) and SignImmSh
    //is the sign extended relative address inputted to the PC ALU

    wire [31:0] SrcA, SrcB; 
    //inputs to the main ALU

    wire [31:0] Result;
    //This is not the alu resut, it is the output of the mux that selects
    //between data memory outout and aluoutput. This is imporatnt as it
    //determines what is written to the register file
    

    Dflipflop PCRegister(PC,Clk, PCNext, Reset);
    //PCRegister


    adder pcadd1(PCPlus4,,1'b0,32'b100,PC); //the adder for the Program counter iteration

    shift_left_2 immsh(SignImmSh,SignImm);
    //shiftng for branch operatioms (multiply by 4)

    adder pcadd2 (PCBranch,,1'b0,SignImmSh,PCPlus4);
    //the adder for branch operations. number of bytes+PC
    
    mux_2_32b pcbrmux(PCNextbr,PCSrc, PCPlus4, PCBranch);                                        //this module is faulty
    //this mux determines if the pc should use the next address(PC+4) or the
    //branched PC (PCBranch) address based on contrrol logic from main dec

    mux_2_32b pcmux(PCNext, Jump,PCNextbr, {PCPlus4[31:28],Instr[25:0], 2'b00});



    


    //register file  //ERROR WITH WriteData
    
    //registerFile(RD1, RD2, A1, A2, A3, WD3, clk, WE3);
    registerFile rf(SrcA, WriteData,Instr[25:21],Instr[20:16],RegisterAddress,Result,Clk, RegWrite);        //ERROR HERE ERROR HERE ERROR HERE


    //mux_2_32b(out, sel, D0, D1); 
    mux_2_5b A3Mux(RegisterAddress,RegDst,Instr[20:16],Instr[25:21]);

    mux_2_32b WD3Mux(Result,MemtoReg,ALUOut, ReadData);

    SignExtender se(Instr[15:0],SignImm);
    //ALU
    mux_2_32b SRCBmux (SrcB, ALUSrc, WriteData, SignImm);
    
    wire C_out;

    ALU alu_main (Zero, ALUOut,C_out,ALUControl,SrcA, SrcB);




endmodule

module mux_2_5b(out, sel, D0, D1); //for controlling A3

    output [4:0] out;
    input sel;
    input [4:0] D0, D1;
    
    assign out=sel? D1:D0;

endmodule


module MIPS (ALUOut,WriteData,WE, PC,Instr,ReadData,Reset,Clk);

    output  WE; //write enable
    output [31:0] ALUOut,WriteData;
    output [31:0] PC;
    input [31:0] Instr, ReadData;
    input Reset,Clk;

    wire MemToReg, Branch,ALUSrc, RegDst, RegWrite, Jump,PCSrc,Zero;
    wire [2:0] ALUControl;
    
    //controller (ALUControl, PCSrc, MemtoReg,ALUSrc,RegDst,RegWrite, MemWrite, Opcode, Funct, Zero, Jump);
    controller control(ALUControl,PCSrc,MemToReg,ALUSrc,RegDst,RegWrite,WE,Instr[31:26],Instr[5:0],Zero,Jump);


    //datapath(ALUOut, WriteData, PC, Zero, Reset, Clk, ALUControl, PCSrc, MemtoReg, ALUSrc, RegDst, RegWrite, Jump, ReadData,Instr);
    datapath dp(ALUOut, WriteData, PC, Zero, Reset, Clk, ALUControl, PCSrc, MemToReg, ALUSrc, RegDst, RegWrite, Jump, ReadData,Instr);


endmodule


module top(Clk, Reset, WriteData,DataAdr,WE);

    input Clk, Reset;
    output [31:0] WriteData, DataAdr;
    output WE;


    wire [31:0] PC, Instr, ReadData;

    //MIPS (ALUOut,WriteData,WE, PC,Instr,ReadData,Reset,Clk);
    MIPS mips(DataAdr,WriteData,WE,PC,Instr,ReadData,Reset,Clk);

    //instruction_memory(RD, A);
    instruction_memory imem(Instr,PC[7:2]);



    //data_memory(RD,clk,A,WD,WE);    
    data_memory dmem(ReadData, Clk, DataAdr, WriteData, WE);

endmodule

Unpipelined/top.vcd
$date
	Sat Jun  4 21:54:27 2022
$end
$version
	Icarus Verilog
$end
$timescale
	1ns
$end
$scope module And $end
$var wire 32 ! SrcA [31:0] $end
$var wire 32 " SrcB [31:0] $end
$var wire 32 # Y [31:0] $end
$upscope $end
$scope module Or $end
$var wire 32 $ SrcA [31:0] $end
$var wire 32 % SrcB [31:0] $end
$var wire 32 & Y [31:0] $end
$upscope $end
$scope module testbench $end
$var wire 32 ' writedata [31:0] $end
$var wire 32 ( dataadr [31:0] $end
$var wire 1 ) WE $end
$var reg 1 * clk $end
$var reg 1 + reset $end
$scope module dut $end
$var wire 1 * Clk $end
$var wire 1 + Reset $end
$var wire 32 , WriteData [31:0] $end
$var wire 1 ) WE $end
$var wire 32 - ReadData [31:0] $end
$var wire 32 . PC [31:0] $end
$var wire 32 / Instr [31:0] $end
$var wire 32 0 DataAdr [31:0] $end
$scope module dmem $end
$var wire 1 * clk $end
$var wire 1 ) WE $end
$var wire 32 1 WD [31:0] $end
$var wire 32 2 A [31:0] $end
$var reg 32 3 RD [31:0] $end
$upscope $end
$scope module imem $end
$var wire 6 4 A [5:0] $end
$var wire 32 5 RD [31:0] $end
$upscope $end
$scope module mips $end
$var wire 1 * Clk $end
$var wire 32 6 Instr [31:0] $end
$var wire 32 7 ReadData [31:0] $end
$var wire 1 + Reset $end
$var wire 1 8 Zero $end
$var wire 32 9 WriteData [31:0] $end
$var wire 1 ) WE $end
$var wire 1 : RegWrite $end
$var wire 1 ; RegDst $end
$var wire 1 < PCSrc $end
$var wire 32 = PC [31:0] $end
$var wire 1 > MemToReg $end
$var wire 1 ? Jump $end
$var wire 1 @ ALUSrc $end
$var wire 32 A ALUOut [31:0] $end
$var wire 3 B ALUControl [2:0] $end
$scope module control $end
$var wire 6 C Funct [5:0] $end
$var wire 6 D Opcode [5:0] $end
$var wire 1 < PCSrc $end
$var wire 1 8 Zero $end
$var wire 1 : RegWrite $end
$var wire 1 ; RegDst $end
$var wire 1 > MemtoReg $end
$var wire 1 ) MemWrite $end
$var wire 1 ? Jump $end
$var wire 1 E Branch $end
$var wire 1 @ ALUSrc $end
$var wire 2 F ALUOp [1:0] $end
$var wire 3 G ALUControl [2:0] $end
$scope module aludec1 $end
$var wire 6 H funct [5:0] $end
$var wire 2 I AluOP [1:0] $end
$var reg 3 J AluControl [2:0] $end
$upscope $end
$scope module md1 $end
$var wire 6 K Opcode [5:0] $end
$var wire 1 : RegWrite $end
$var wire 1 ; RegDst $end
$var wire 1 > MemtoReg $end
$var wire 1 ) MemWrite $end
$var wire 1 ? Jump $end
$var wire 1 E Branch $end
$var wire 1 @ ALUSrc $end
$var wire 2 L ALUOp [1:0] $end
$var reg 9 M controls [8:0] $end
$upscope $end
$upscope $end
$scope module dp $end
$var wire 3 N ALUControl [2:0] $end
$var wire 1 @ ALUSrc $end
$var wire 1 * Clk $end
$var wire 32 O Instr [31:0] $end
$var wire 1 ? Jump $end
$var wire 1 > MemtoReg $end
$var wire 1 < PCSrc $end
$var wire 32 P ReadData [31:0] $end
$var wire 1 ; RegDst $end
$var wire 1 : RegWrite $end
$var wire 1 + Reset $end
$var wire 1 8 Zero $end
$var wire 32 Q WriteData [31:0] $end
$var wire 32 R SrcB [31:0] $end
$var wire 32 S SrcA [31:0] $end
$var wire 32 T SignImmSh [31:0] $end
$var wire 32 U SignImm [31:0] $end
$var wire 32 V Result [31:0] $end
$var wire 5 W RegisterAddress [4:0] $end
$var wire 32 X PCPlus4 [31:0] $end
$var wire 32 Y PCNextbr [31:0] $end
$var wire 32 Z PCNext [31:0] $end
$var wire 32 [ PCBranch [31:0] $end
$var wire 32 \ PC [31:0] $end
$var wire 1 ] C_out $end
$var wire 32 ^ ALUOut [31:0] $end
$scope module A3Mux $end
$var wire 5 _ D0 [4:0] $end
$var wire 5 ` D1 [4:0] $end
$var wire 1 ; sel $end
$var wire 5 a out [4:0] $end
$upscope $end
$scope module PCRegister $end
$var wire 1 * clk $end
$var wire 1 + reset $end
$var wire 32 b D [31:0] $end
$var reg 32 c Q [31:0] $end
$upscope $end
$scope module SRCBmux $end
$var wire 1 @ sel $end
$var wire 32 d out [31:0] $end
$var wire 32 e D1 [31:0] $end
$var wire 32 f D0 [31:0] $end
$upscope $end
$scope module WD3Mux $end
$var wire 32 g D1 [31:0] $end
$var wire 1 > sel $end
$var wire 32 h out [31:0] $end
$var wire 32 i D0 [31:0] $end
$upscope $end
$scope module alu_main $end
$var wire 3 j ALUControl [2:0] $end
$var wire 32 k N0 [31:0] $end
$var wire 32 l N1 [31:0] $end
$var wire 32 m SrcB [31:0] $end
$var wire 32 n SrcB_not [31:0] $end
$var wire 32 o mux1_out [31:0] $end
$var wire 1 8 Zero $end
$var wire 32 p SrcA [31:0] $end
$var wire 32 q N3 [31:0] $end
$var wire 32 r N2 [31:0] $end
$var wire 1 ] C_out $end
$var wire 32 s ALUResult [31:0] $end
$scope module add1 $end
$var wire 1 t C_in $end
$var wire 32 u Y [31:0] $end
$var wire 32 v SrcB [31:0] $end
$var wire 32 w SrcA [31:0] $end
$var wire 1 ] C_out $end
$upscope $end
$scope module mux1 $end
$var wire 32 x D0 [31:0] $end
$var wire 32 y D1 [31:0] $end
$var wire 1 z sel $end
$var wire 32 { out [31:0] $end
$upscope $end
$scope module mux2 $end
$var wire 32 | D0 [31:0] $end
$var wire 32 } D1 [31:0] $end
$var wire 32 ~ D2 [31:0] $end
$var wire 32 !" D3 [31:0] $end
$var wire 2 "" sel [1:0] $end
$var wire 32 #" out [31:0] $end
$upscope $end
$upscope $end
$scope module immsh $end
$var wire 32 $" shifted_out [31:0] $end
$var wire 32 %" shift_in [31:0] $end
$upscope $end
$scope module pcadd1 $end
$var wire 1 &" C_in $end
$var wire 32 '" SrcA [31:0] $end
$var wire 32 (" SrcB [31:0] $end
$var wire 32 )" Y [31:0] $end
$var wire 1 *" C_out $end
$upscope $end
$scope module pcadd2 $end
$var wire 1 +" C_in $end
$var wire 32 ," SrcA [31:0] $end
$var wire 32 -" SrcB [31:0] $end
$var wire 32 ." Y [31:0] $end
$var wire 1 /" C_out $end
$upscope $end
$scope module pcbrmux $end
$var wire 32 0" D0 [31:0] $end
$var wire 32 1" D1 [31:0] $end
$var wire 1 < sel $end
$var wire 32 2" out [31:0] $end
$upscope $end
$scope module pcmux $end
$var wire 32 3" D0 [31:0] $end
$var wire 32 4" D1 [31:0] $end
$var wire 1 ? sel $end
$var wire 32 5" out [31:0] $end
$upscope $end
$scope module rf $end
$var wire 5 6" A1 [4:0] $end
$var wire 5 7" A2 [4:0] $end
$var wire 5 8" A3 [4:0] $end
$var wire 32 9" WD3 [31:0] $end
$var wire 1 : WE3 $end
$var wire 1 * clk $end
$var wire 32 :" RD2 [31:0] $end
$var wire 32 ;" RD1 [31:0] $end
$upscope $end
$scope module se $end
$var wire 16 <" extend [15:0] $end
$var wire 32 =" extended [31:0] $end
$upscope $end
$upscope $end
$upscope $end
$upscope $end
$upscope $end
$enddefinitions $end
#0
$dumpvars
b101 ="
b101 <"
b0 ;"
bx :"
b101 9"
b10 8"
b10 7"
b0 6"
b100 5"
b10000000000000010100 4"
b100 3"
b100 2"
b11000 1"
b100 0"
0/"
b11000 ."
b100 -"
b10100 ,"
0+"
0*"
b100 )"
b0 ("
b100 '"
0&"
b101 %"
b10100 $"
b101 #"
b10 ""
b101 !"
b101 ~
b0 }
b0 |
b101 {
0z
b11111111111111111111111111111010 y
b101 x
b101 w
b0 v
b101 u
0t
b101 s
b101 r
b101 q
b0 p
b101 o
b11111111111111111111111111111010 n
b101 m
b0 l
b0 k
b10 j
b101 i
b101 h
bx g
bx f
b101 e
b101 d
b0 c
b100 b
b10 a
b0 `
b10 _
b101 ^
0]
b0 \
b11000 [
b100 Z
b100 Y
b100 X
b10 W
b101 V
b101 U
b10100 T
b0 S
b101 R
bx Q
bx P
b100000000000100000000000000101 O
b10 N
b101000000 M
b0 L
b1000 K
b10 J
b0 I
b101 H
b10 G
b0 F
0E
b1000 D
b101 C
b10 B
b101 A
1@
0?
0>
b0 =
0<
0;
1:
bx 9
08
bx 7
b100000000000100000000000000101 6
b100000000000100000000000000101 5
b0 4
bx 3
b101 2
bx 1
b101 0
b100000000000100000000000000101 /
b0 .
bx -
bx ,
1+
1*
0)
b101 (
bx '
bx &
bz %
bz $
bx #
bz "
bz !
$end
#5
0*
#10
b101 '
b101 ,
b101 1
b101 9
b101 Q
b101 f
b101 :"
1*
#15
0*
#20
1*
#22
0+
#25
0*
#30
b1100 V
b1100 h
b1100 9"
b1100 (
b1100 0
b1100 2
b1100 A
b1100 ^
b1100 i
b1100 s
b1100 #"
b1100 q
b1100 !"
b1100 r
b1100 u
b1100 ~
b11111111111111111111111111110011 n
b11111111111111111111111111110011 y
b1100 o
b1100 w
b1100 {
b1000 Z
b1000 b
b1000 5"
bx '
bx ,
bx 1
bx 9
bx Q
bx f
bx :"
b11 W
b11 a
b11 8"
b110000 T
b110000 $"
b110000 ,"
b1100 R
b1100 d
b1100 m
b1100 x
b111000 [
b111000 ."
b111000 1"
b1000 Y
b1000 2"
b1000 3"
b1100 C
b1100 H
b11000000000000110000 4"
b11 7"
b11 _
b1100 U
b1100 e
b1100 %"
b1100 ="
b1100 <"
b1000 X
b1000 )"
b1000 -"
b1000 0"
b100000000000110000000000001100 /
b100000000000110000000000001100 5
b100000000000110000000000001100 6
b100000000000110000000000001100 O
b1 4
b100 .
b100 =
b100 \
b100 c
b100 ("
1*
#35
0*
#40
b11 V
b11 h
b11 9"
b11 (
b11 0
b11 2
b11 A
b11 ^
b11 i
b11 s
b11 #"
1]
b11 q
b11 !"
b11 r
b11 u
b11 ~
b100 l
b100 }
b100 k
b100 |
b1000 n
b1000 y
b11111111111111111111111111110111 o
b11111111111111111111111111110111 w
b11111111111111111111111111110111 {
b1100 Z
b1100 b
b1100 5"
b1100 S
b1100 p
b1100 v
b1100 ;"
b111 W
b111 a
b111 8"
b11111111111111111111111111011100 T
b11111111111111111111111111011100 $"
b11111111111111111111111111011100 ,"
b11111111111111111111111111110111 R
b11111111111111111111111111110111 d
b11111111111111111111111111110111 m
b11111111111111111111111111110111 x
b11111111111111111111111111101000 [
b11111111111111111111111111101000 ."
b11111111111111111111111111101000 1"
b1100 Y
b1100 2"
b1100 3"
b110111 C
b110111 H
b1100111111111111111011100 4"
b11 6"
b111 7"
b111 _
b11 `
b11111111111111111111111111110111 U
b11111111111111111111111111110111 e
b11111111111111111111111111110111 %"
b11111111111111111111111111110111 ="
b1111111111110111 <"
bx '
bx ,
bx 1
bx 9
bx Q
bx f
bx :"
b1100 X
b1100 )"
b1100 -"
b1100 0"
b100000011001111111111111110111 /
b100000011001111111111111110111 5
b100000011001111111111111110111 6
b100000011001111111111111110111 O
b10 4
b1000 .
b1000 =
b1000 \
b1000 c
b1000 ("
1*
#45
0*
#50
1z
1t
b110 B
b110 G
b110 J
b110 N
b110 j
1;
0@
b1 F
b1 I
b1 L
b110000010 M
b11111111111111111111111111111110 V
b11111111111111111111111111111110 h
b11111111111111111111111111111110 9"
b11111111111111111111111111111110 (
b11111111111111111111111111111110 0
b11111111111111111111111111111110 2
b11111111111111111111111111111110 A
b11111111111111111111111111111110 ^
b11111111111111111111111111111110 i
b11111111111111111111111111111110 s
b11111111111111111111111111111110 #"
b1111111111111111111111111111110 q
b1111111111111111111111111111110 !"
b11111111111111111111111111111110 r
b11111111111111111111111111111110 u
b11111111111111111111111111111110 ~
0]
b10 l
b10 }
b10 k
b10 |
b11111111111111111111111111111010 n
b11111111111111111111111111111010 y
b11111111111111111111111111111010 o
b11111111111111111111111111111010 w
b11111111111111111111111111111010 {
b10000 Z
b10000 b
b10000 5"
b11 S
b11 p
b11 v
b11 ;"
b111 W
b111 a
b111 8"
b1000000010010100 T
b1000000010010100 $"
b1000000010010100 ,"
b101 R
b101 d
b101 m
b101 x
b1000000010100100 [
b1000000010100100 ."
b1000000010100100 1"
b10000 Y
b10000 2"
b10000 3"
b0 D
b0 K
b100101 C
b100101 H
b11100010001000000010010100 4"
b111 6"
b10 7"
b10 _
b111 `
b10000000100101 U
b10000000100101 e
b10000000100101 %"
b10000000100101 ="
b10000000100101 <"
b101 '
b101 ,
b101 1
b101 9
b101 Q
b101 f
b101 :"
b10000 X
b10000 )"
b10000 -"
b10000 0"
b111000100010000000100101 /
b111000100010000000100101 5
b111000100010000000100101 6
b111000100010000000100101 O
b11 4
b1100 .
b1100 =
b1100 \
b1100 c
b1100 ("
1*
#55
0*
#60
x8
bx o
bx w
bx {
bx V
bx h
bx 9"
bx n
bx y
bx (
bx 0
bx 2
bx A
bx ^
bx i
bx s
bx #"
bx R
bx d
bx m
bx x
b0xxxxxxxxxxxxxxxxxxxxxxxxxxxxxxx q
b0xxxxxxxxxxxxxxxxxxxxxxxxxxxxxxx !"
b10100 Z
b10100 b
b10100 5"
bx '
bx ,
bx 1
bx 9
bx Q
bx f
bx :"
b11 W
b11 a
b11 8"
b1010000010010000 T
b1010000010010000 $"
b1010000010010000 ,"
bx r
bx u
bx ~
x]
b0xx00 l
b0xx00 }
b0xx00 k
b0xx00 |
b1010000010100100 [
b1010000010100100 ."
b1010000010100100 1"
b10100 Y
b10100 2"
b10100 3"
b100100 C
b100100 H
b1100100001010000010010000 4"
b11 6"
b100 7"
b100 _
b11 `
b10100000100100 U
b10100000100100 e
b10100000100100 %"
b10100000100100 ="
b10100000100100 <"
b1100 S
b1100 p
b1100 v
b1100 ;"
b10100 X
b10100 )"
b10100 -"
b10100 0"
b11001000010100000100100 /
b11001000010100000100100 5
b11001000010100000100100 6
b11001000010100000100100 O
b100 4
b10000 .
b10000 =
b10000 \
b10000 c
b10000 ("
1*
#65
0*
#70
b11000 Z
b11000 b
b11000 5"
b101 W
b101 a
b101 8"
b1010000010000000 T
b1010000010000000 $"
b1010000010000000 ,"
bx l
bx }
bx k
bx |
b1010000010011000 [
b1010000010011000 ."
b1010000010011000 1"
b11000 Y
b11000 2"
b11000 3"
b100000 C
b100000 H
b10100100001010000010000000 4"
b101 6"
b101 `
b10100000100000 U
b10100000100000 e
b10100000100000 %"
b10100000100000 ="
b10100000100000 <"
bx S
bx p
bx v
bx ;"
b11000 X
b11000 )"
b11000 -"
b11000 0"
b101001000010100000100000 /
b101001000010100000100000 5
b101001000010100000100000 6
b101001000010100000100000 O
b101 4
b10100 .
b10100 =
b10100 \
b10100 c
b10100 ("
1*
#75
0*
#80
0z
0t
b10 B
b10 G
b10 J
b10 N
b10 j
b111 W
b111 a
b111 8"
x<
0:
0;
1E
b0 F
b0 I
b0 L
1?
b100001 M
bx0 l
bx0 }
bx0 k
bx0 |
b11111111111111111111111111111110 o
b11111111111111111111111111111110 w
b11111111111111111111111111111110 {
b1 n
b1 y
b11111111111111111111111111111110 R
b11111111111111111111111111111110 d
b11111111111111111111111111111110 m
b11111111111111111111111111111110 x
b10100111000000000000101000 Z
b10100111000000000000101000 b
b10100111000000000000101000 5"
b11111111111111111111111111111110 '
b11111111111111111111111111111110 ,
b11111111111111111111111111111110 1
b11111111111111111111111111111110 9
b11111111111111111111111111111110 Q
b11111111111111111111111111111110 f
b11111111111111111111111111111110 :"
b101000 T
b101000 $"
b101000 ,"
b1000100 [
b1000100 ."
b1000100 1"
b0x0xx100 Y
b0x0xx100 2"
b0x0xx100 3"
b100 D
b100 K
b1010 C
b1010 H
b10100111000000000000101000 4"
b111 7"
b111 _
b1010 U
b1010 e
b1010 %"
b1010 ="
b1010 <"
b11100 X
b11100 )"
b11100 -"
b11100 0"
b10000101001110000000000001010 /
b10000101001110000000000001010 5
b10000101001110000000000001010 6
b10000101001110000000000001010 O
b110 4
b11000 .
b11000 =
b11000 \
b11000 c
b11000 ("
1*
#85
0*
