Multicycle/Controller_tb.v
`include "MIPS_Multicycle.v"




module Controller_tb;


    wire [1:0] ALUOp, ALUSrcB;
    wire MemtoReg,MemWrite,RegDst,RegWrite,Jump, 
    IorD, PCSrc,ALUSrcA,IRWrite,PCWrite,Branch;


    reg [5:0] Opcode;
    reg Clk,Reset;


    initial begin 

        $display("starting controller test");
        $dumpfile("Controller.vcd");
        $dumpvars;
    end


    mainDecoder dut(Opcode,Clk,Reset,MemtoReg,MemWrite,RegDst,RegWrite,Jump,ALUOp, IorD, PCSrc,ALUSrcB,ALUSrcA,IRWrite,PCWrite,Branch);


    initial begin
        //Opcode<=6'b100011;#10; //load 
        //Opcode<=6'b101011;#10;   //store
        Opcode<=6'b000000;#10;     //r type
        //Opcode<=6'b000101;#10;     //BEQ
        //6'001000: nextstate=S9;    //ADDI
    end


    initial begin 
        #150; $stop;
    end


    initial begin 
        Reset<=1; #10; Reset<=0;
    end


    always begin
        Clk<=0; #10; Clk<=1; #10;
    end


endmodule

Multicycle/MIPS_Multicycle.v
//on reset PC should begin at 0xBFC0 0000



//32 bit flip flop with active high reset 
module flopr #(parameter WIDTH = 8) (Clk,Reset, d, q);

    input Clk, Reset;
    input [WIDTH-1:0] d;
    output reg [WIDTH-1:0] q;

    
    always @ (posedge Clk,posedge Reset)
        if(Reset) q<=0;
        else q<=d; //output new PC from alu on posedge Clk 
endmodule


module mux2 #(parameter WIDTH = 8) (d0,d1,s,y);

    input [WIDTH-1:0] d0, d1;
    input s;
    output [WIDTH-1:0] y;

    assign y=s?d1:d0;

endmodule


//register file. Contains 32 internal registers. each 32 bits wide
//address 1 (A1) is read to RD1 asynchronously. Same is true for A2 and RD2.
//To write, input address is A3. Address to read is WD3. occurs on posedge Clk
//write enable must also be active. 
module registerFile(Clk,WE3,A1,A2,A3,WD3,RD1,RD2);
    
    output [31:0] RD1, RD2;  //outputs of the register file are each 32 bits since the regsiter is 32 bits wide
    input [4:0] A1,A2,A3;   //2^5=32 since 32 total addresses
    input [31:0] WD3; //the data to be written if WE3 is high 
    input Clk, WE3; 

    reg [31:0] internal_mem [31:0]; //32 wires each 32 bits long

    
        always @ (posedge Clk) 
            if (WE3) internal_mem[A3]<=WD3;
        

    assign RD1 = (A1 !=0) ? internal_mem[A1] :0;
    assign RD2 = (A2 !=0) ? internal_mem[A2] :0;

endmodule


//in single cycle mips architecture, the program and variables are stored in
//two seperate registers. Instruction memory stores the program, Data memory
//(TBD) stores variable information
module Instruction_memory(A, RD);
    output [31:0] RD;    //output data is 32 bits wide because thats how long Instructions are
    input [5:0] A;      //64 possible addresses

    reg [31:0] RAM [63:0]; //64 wires each 32 bits wide
    
    initial
        begin 
            $readmemh("memfile.dat",RAM); //read dissassembled MIPS code and load it into ram
    end

    assign RD = RAM[A]; //output onto bus. no need for clock because ram is asynchronous

endmodule




//more ram. This is where data is written during program exectuion. 
//writing is done on the clock, reading is done asynchronously
//input address is 32 bits, data width is 32 bits. 
module data_memory(Clk, WE, A, WD, RD);
    //not using full memory capabilities
    //

    output reg [31:0] RD;
    input Clk, WE;
    input [31:0] A,WD;


    reg [31:0] data [63:0];


//    assign RD = data[A[31:2]]; //address is always being read out

  //  always @ (posedge Clk)
    //    if(WE==1) data[A[31:2]] <=WD;

    always @(*) begin
        RD<=data[A[31:2]];
    end

    //assign RD=data[A[31:2]];

    always @ (posedge Clk)
        if(WE) data[A[31:2]] <=WD;

endmodule



module SignExtender(extend, extended);

    input [15:0] extend;
    output [31:0] extended;

    assign extended[31:0]= {{16{extend[15]}},extend[15:0]};

endmodule

module adder(Y,C_out,C_in,SrcA, SrcB);

    output [31:0] Y;
    output C_out;
    input [31:0] SrcA, SrcB;
    input C_in;
    

    assign {C_out,Y}=SrcA+SrcB+C_in;


endmodule







module Or(Y, SrcA,SrcB);

    output [31:0] Y;
    input [31:0] SrcA, SrcB;


    assign Y=SrcA | SrcB;

endmodule

module And(Y, SrcA,SrcB);

    output [31:0] Y;
    input [31:0] SrcA, SrcB;


    assign Y=SrcA & SrcB;

endmodule
//subtract and add are done the same exact way. the only difference is that 
//subtract is compiled as the addition of a twos complement number to
//a posative 
module ALU(Zero, ALUResult, C_out, ALUControl, SrcA, SrcB);

    output Zero;
    output [31:0] ALUResult;
    output C_out;
    input [2:0] ALUControl;
    input [31:0] SrcA, SrcB;
    
    wire [31:0] SrcB_not; assign SrcB_not=~SrcB;
    wire [31:0] mux1_out;
    wire [31:0] N0,N1,N2,N3;


    mux_2_32b mux1(mux1_out,ALUControl[2], SrcB,SrcB_not);
 
    assign N0=mux1_out&SrcA;

    assign N1=mux1_out|SrcA;


    adder add1(N2,C_out,ALUControl[2],mux1_out,SrcA);
    assign N3={N2[31]};

    mux_4_32b mux2(ALUResult,ALUControl[1:0],N0,N1,N2,N3);


    assign Zero = (ALUResult==0) ?   1 :0;

endmodule








module shift_left_2(shifted_out,shift_in);

    input [31:0] shift_in;
    output [31:0] shifted_out;


    assign shifted_out=shift_in<<2;
endmodule


module mux_2_32b(out, sel, D0, D1);

    output [31:0] out;
    input sel;
    input [31:0] D0, D1;
    
    assign out=sel? D1:D0;

endmodule


module mux_4_32b(out, sel, D0, D1, D2, D3);

    output [31:0] out;
    input [1:0]sel;
    input [31:0] D0, D1, D2, D3;
    
    assign out=sel[1]? (sel[0]?D3:D2):(sel[0]? D1: D0);

endmodule



//The input to the alu control logic depends on 2 things, the op code and the
//funct space (in R type Instructions). For instance, an Instruction with
//opcode 000000 is always going to have an AluOp of 10. 10 indicates that the
//ALUControl depends on the funct field of the Instruction, (Or, Nor, Add all
//work differently). However, in I type Instructions, there is no funct field,
//so the alu controll only depends on the opcode, and the logic for that is
//quite straight forward. 

//ALU decoder controls the operation that occurs in the alu

//ALU decoder stays the same relative to single cycle 
module AluDecoder(Funct,AluOP,ALUControl);

    output reg [2:0]ALUControl;
    input [1:0] AluOP;
    input [5:0] Funct;
    

    always @ (*)
        case (AluOP)
            2'b00: ALUControl <=3'b010;
            2'b01: ALUControl <=3'b110;
            default: case(Funct)
                6'b100000 : ALUControl <= 3'b010;   //add
                6'b100010 : ALUControl <= 3'b110;   //sub
                6'b100100 : ALUControl <= 3'b000;   //and
                6'b100101 : ALUControl <= 3'b001;   //or
                6'b101010 : ALUControl <= 3'b111;   //slt
                default: ALUControl <=3'bxxx;
            endcase
        endcase


        
endmodule



//main decoder takes in opcode and outputs multiplexer selects and register enables
//IMP: it also outputs ALUOp which goes into the ALU decoder to control the operation of the ALU
//Since this MIPS implementation is multi cycle, a state machine needs to controll the control signals based on the clock number (and instruction) its executing.

module mainDecoder(Opcode,Clk,Reset,MemtoReg,MemWrite,RegDst,RegWrite,Jump,ALUOp, 
                    IorD, PCSrc,ALUSrcB,ALUSrcA,IRWrite,PCWrite,Branch); //TODO


    input [5:0] Opcode;
    input Clk,Reset;
    output reg MemtoReg,MemWrite,RegDst,RegWrite,Jump, 
    IorD, PCSrc,ALUSrcA,IRWrite,PCWrite,Branch;
    output reg [1:0] ALUOp, ALUSrcB;


    reg [3:0] state,nextstate;



    //PARAMETERS (States)

    parameter S0=4'b0000;
    parameter S1=4'b0001;
    parameter S2=4'b0010;
    parameter S3=4'b0011;
    parameter S4=4'b0100;
    parameter S5=4'b0101;
    parameter S6=4'b0110;
    parameter S7=4'b0111;
    parameter S8=4'b1000;
    parameter S9=4'b1001;
    parameter S10=4'b1010;


    always @ (posedge  Clk, posedge Reset)
        if (Reset) state<=S0;
        else state <=nextstate;

    always @(*) //convers state transitions
        case (state)
            S0: nextstate=S1;
            S1: case(Opcode)
                6'b100011: nextstate=S2;    //load 
                6'b101011: nextstate=S2;    //store
                6'b000000: nextstate=S6;     //r type
                6'b000101: nextstate=S8;     //BEQ
                6'001000: nextstate=S9;     //ADDI
                endcase

            S2: case(Opcode)
                6'b100011: nextstate=S3;    //load 
                6'b101011: nextstate=S5;    //store
                endcase

            S3: nextstate=S4;
            S4: nextstate=S0;
            S5: nextstate=S0;
            S6: nextstate=S7;
            S7: nextstate=S0;
            S8: nextstate=S0;
            S9: nextstate=S10;
            S10:nextstate=S10;




        endcase

    

 always @(*) 
        begin//covers outputs (output logic)
            casex (state)   
                S0: begin

                    MemtoReg=1'bx;
                    MemWrite=1'bx;
                    RegDst=1'bx;
                    RegWrite=1'bx;
                    Jump=1'bx;
                    IorD=1'b0; 
                    PCSrc=1'b0;
                    ALUSrcA=1'b0;
                    IRWrite=1'b1;
                    PCWrite=1'b1;
                    Branch=1'bx;
                    ALUOp=2'b00;
                    ALUSrcB=2'b01;  
                end

                S1: begin
                    MemtoReg=1'bx;
                    MemWrite=1'bx;
                    RegDst=1'bx;
                    RegWrite=1'bx;
                    Jump=1'bx;
                    IorD=1'bx; 
                    PCSrc=1'bx;
                    ALUSrcA=1'b0;
                    IRWrite=1'bx;
                    PCWrite=1'bx;
                    Branch=1'bx;
                    ALUOp=2'b00;
                    ALUSrcB=2'b11;
                end
                
                S2: begin
                    MemtoReg=1'bx;
                    MemWrite=1'bx;
                    RegDst=1'bx;
                    RegWrite=1'bx;
                    Jump=1'bx; 
                    IorD=1'bx; 
                    PCSrc=1'bx;
                    ALUSrcA=1'b1;
                    IRWrite=1'bx;
                    PCWrite=1'bx;
                    Branch=1'bx;
                    ALUOp=2'b00;
                    ALUSrcB=2'b10;
                end

                S3: begin
                    MemtoReg=1'bx;
                    MemWrite=1'bx;
                    RegDst=1'bx;
                    RegWrite=1'bx;
                    Jump=1'bx;
                    IorD=1'b1; 
                    PCSrc=1'bx;
                    ALUSrcA=1'bx;
                    IRWrite=1'bx;
                    PCWrite=1'bx;
                    Branch=1'bx;
                    ALUOp=2'bxx;
                    ALUSrcB=2'bxx;
                end


                S4: begin
                    MemtoReg=1'b1;
                    MemWrite=1'bx;
                    RegDst=1'b0;
                    RegWrite=1'b1;
                    Jump=1'bx;
                    IorD=1'bx; 
                    PCSrc=1'bx;
                    ALUSrcA=1'bx;
                    IRWrite=1'bx;
                    PCWrite=1'bx;
                    Branch=1'bx;
                    ALUOp=2'bxx;
                    ALUSrcB=2'bxx;
                end
                
                S5: begin
                    MemtoReg=1'bx;
                    MemWrite=1'b1;
                    RegDst=1'bx;
                    RegWrite=1'bx;
                    Jump=1'bx;
                    IorD=1'b1; 
                    PCSrc=1'bx;
                    ALUSrcA=1'bx;
                    IRWrite=1'bx;
                    PCWrite=1'bx;
                    Branch=1'bx;
                    ALUOp=2'bxx;
                    ALUSrcB=2'bxx;
                end

                S6: begin
                    MemtoReg=1'bx;
                    MemWrite=1'bx;
                    RegDst=1'bx;
                    RegWrite=1'bx;
                    Jump=1'bx;
                    IorD=1'bx; 
                    PCSrc=1'bx;
                    ALUSrcA=1'b1;
                    IRWrite=1'bx;
                    PCWrite=1'bx;
                    Branch=1'bx;
                    ALUOp=2'b10;
                    ALUSrcB=2'b00;
                end

                S7: begin
                    MemtoReg=1'b0;
                    MemWrite=1'bx;
                    RegDst=1'b1;
                    RegWrite=1'b1;
                    Jump=1'bx;
                    IorD=1'bx; 
                    PCSrc=1'bx;
                    ALUSrcA=1'bx;
                    IRWrite=1'bx;
                    PCWrite=1'bx;
                    Branch=1'bx;
                    ALUOp=2'bxx;
                    ALUSrcB=2'bxx;
                end

                S8: begin
                    MemtoReg=1'bx;
                    MemWrite=1'bx;
                    RegDst=1'bx;
                    RegWrite=1'bx;
                    Jump=1'bx;
                    IorD=1'bx; 
                    PCSrc=1'b1;
                    ALUSrcA=1'b1;
                    IRWrite=1'bx;
                    PCWrite=1'bx;
                    Branch=1'b1;
                    ALUOp=2'b01;
                    ALUSrcB=2'b00;
                end

                S9: begin
                    MemtoReg=1'bx;
                    MemWrite=1'bx;
                    RegDst=1'bx;
                    RegWrite=1'bx;
                    Jump=1'bx;
                    IorD=1'bx; 
                    PCSrc=1'bx;
                    ALUSrcA=1'b1;
                    IRWrite=1'bx;
                    PCWrite=1'bx;
                    Branch=1'bx;
                    ALUOp=2'b00;
                    ALUSrcB=2'b10;
                end
                S10: begin
                    MemtoReg=1'b0;
                    MemWrite=1'bx;
                    RegDst=1'b1;
                    RegWrite=1'b1;
                    Jump=1'bx;
                    IorD=1'bx; 
                    PCSrc=1'bx;
                    ALUSrcA=1'bx;
                    IRWrite=1'bx;
                    PCWrite=1'bx;
                    Branch=1'bx;
                    ALUOp=2'bxx;
                    ALUSrcB=2'bxx;
                end
            endcase
        end
        




endmodule




module controller (Opcode,Funct,Zero,Clk,MemtoReg,MemWrite,PCSrc,RegDst,RegWrite,ALUControl,Branch, IorD,IRWrite, PCWrite,ALUSrcB,ALUSrcA,PCEn);


    //TODO

    input [5:0] Opcode, Funct;
    input Zero,Clk;

    output MemtoReg,MemWrite,PCSrc,RegDst,RegWrite,Branch, IorD,IRWrite, PCWrite,ALUSrcA,PCEn;
    output [5:0] ALUControl;
    output [1:0] ALUSrcB;





endmodule


/*
module datapath(Clk,Reset,MemtoReg,PCSrc,ALUSrc,RegDst,RegWrite,Jump,ALUControl,Zero,PC,Instr,ALUOut,WriteData,ReadData); //TODO
 






endmodule*/

module mux_2_5b(out, sel, D0, D1); //for controlling A3

    output [4:0] out;
    input sel;
    input [4:0] D0, D1;
    
    assign out=sel? D1:D0;

endmodule

/**
module MIPS (Clk,reset,PC,Instr,memwrite,ALUOut,writedata,ReadData);     //TODO






endmodule


module top(Clk, Reset, WriteData,DataAdr,MemWrite); //TODO

endmodule
**/

Multicycle/Controller.vcd
$date
	Wed Jun  8 23:55:40 2022
$end
$version
	Icarus Verilog
$end
$timescale
	1s
$end
$scope module ALU $end
$var wire 3 ! ALUControl [2:0] $end
$var wire 32 " N0 [31:0] $end
$var wire 32 # N1 [31:0] $end
$var wire 32 $ SrcA [31:0] $end
$var wire 32 % SrcB [31:0] $end
$var wire 32 & SrcB_not [31:0] $end
$var wire 32 ' mux1_out [31:0] $end
$var wire 1 ( Zero $end
$var wire 32 ) N3 [31:0] $end
$var wire 32 * N2 [31:0] $end
$var wire 1 + C_out $end
$var wire 32 , ALUResult [31:0] $end
$scope module add1 $end
$var wire 1 - C_in $end
$var wire 32 . SrcB [31:0] $end
$var wire 32 / Y [31:0] $end
$var wire 32 0 SrcA [31:0] $end
$var wire 1 + C_out $end
$upscope $end
$scope module mux1 $end
$var wire 32 1 D0 [31:0] $end
$var wire 32 2 D1 [31:0] $end
$var wire 1 3 sel $end
$var wire 32 4 out [31:0] $end
$upscope $end
$scope module mux2 $end
$var wire 32 5 D0 [31:0] $end
$var wire 32 6 D1 [31:0] $end
$var wire 32 7 D2 [31:0] $end
$var wire 32 8 D3 [31:0] $end
$var wire 2 9 sel [1:0] $end
$var wire 32 : out [31:0] $end
$upscope $end
$upscope $end
$scope module AluDecoder $end
$var wire 2 ; AluOP [1:0] $end
$var wire 6 < Funct [5:0] $end
$var reg 3 = ALUControl [2:0] $end
$upscope $end
$scope module And $end
$var wire 32 > SrcA [31:0] $end
$var wire 32 ? SrcB [31:0] $end
$var wire 32 @ Y [31:0] $end
$upscope $end
$scope module Controller_tb $end
$var wire 1 A RegWrite $end
$var wire 1 B RegDst $end
$var wire 1 C PCWrite $end
$var wire 1 D PCSrc $end
$var wire 1 E MemtoReg $end
$var wire 1 F MemWrite $end
$var wire 1 G Jump $end
$var wire 1 H IorD $end
$var wire 1 I IRWrite $end
$var wire 1 J Branch $end
$var wire 2 K ALUSrcB [1:0] $end
$var wire 1 L ALUSrcA $end
$var wire 2 M ALUOp [1:0] $end
$var reg 1 N Clk $end
$var reg 6 O Opcode [5:0] $end
$var reg 1 P Reset $end
$scope module dut $end
$var wire 1 N Clk $end
$var wire 6 Q Opcode [5:0] $end
$var wire 1 P Reset $end
$var reg 2 R ALUOp [1:0] $end
$var reg 1 L ALUSrcA $end
$var reg 2 S ALUSrcB [1:0] $end
$var reg 1 J Branch $end
$var reg 1 I IRWrite $end
$var reg 1 H IorD $end
$var reg 1 G Jump $end
$var reg 1 F MemWrite $end
$var reg 1 E MemtoReg $end
$var reg 1 D PCSrc $end
$var reg 1 C PCWrite $end
$var reg 1 B RegDst $end
$var reg 1 A RegWrite $end
$var reg 4 T nextstate [3:0] $end
$var reg 4 U state [3:0] $end
$upscope $end
$upscope $end
$scope module Instruction_memory $end
$var wire 6 V A [5:0] $end
$var wire 32 W RD [31:0] $end
$upscope $end
$scope module Or $end
$var wire 32 X SrcA [31:0] $end
$var wire 32 Y SrcB [31:0] $end
$var wire 32 Z Y [31:0] $end
$upscope $end
$scope module SignExtender $end
$var wire 16 [ extend [15:0] $end
$var wire 32 \ extended [31:0] $end
$upscope $end
$scope module controller $end
$var wire 6 ] ALUControl [5:0] $end
$var wire 1 ^ ALUSrcA $end
$var wire 2 _ ALUSrcB [1:0] $end
$var wire 1 ` Branch $end
$var wire 1 a Clk $end
$var wire 6 b Funct [5:0] $end
$var wire 1 c IRWrite $end
$var wire 1 d IorD $end
$var wire 1 e MemWrite $end
$var wire 1 f MemtoReg $end
$var wire 6 g Opcode [5:0] $end
$var wire 1 h PCEn $end
$var wire 1 i PCSrc $end
$var wire 1 j PCWrite $end
$var wire 1 k RegDst $end
$var wire 1 l RegWrite $end
$var wire 1 m Zero $end
$upscope $end
$scope module data_memory $end
$var wire 32 n A [31:0] $end
$var wire 1 o Clk $end
$var wire 32 p WD [31:0] $end
$var wire 1 q WE $end
$var reg 32 r RD [31:0] $end
$upscope $end
$scope module flopr $end
$var wire 1 s Clk $end
$var wire 1 t Reset $end
$var wire 8 u d [7:0] $end
$var reg 8 v q [7:0] $end
$upscope $end
$scope module mux2 $end
$var wire 8 w d0 [7:0] $end
$var wire 8 x d1 [7:0] $end
$var wire 1 y s $end
$var wire 8 z y [7:0] $end
$upscope $end
$scope module mux_2_5b $end
$var wire 5 { D0 [4:0] $end
$var wire 5 | D1 [4:0] $end
$var wire 1 } sel $end
$var wire 5 ~ out [4:0] $end
$upscope $end
$scope module registerFile $end
$var wire 5 !" A1 [4:0] $end
$var wire 5 "" A2 [4:0] $end
$var wire 5 #" A3 [4:0] $end
$var wire 1 $" Clk $end
$var wire 32 %" WD3 [31:0] $end
$var wire 1 &" WE3 $end
$var wire 32 '" RD2 [31:0] $end
$var wire 32 (" RD1 [31:0] $end
$upscope $end
$scope module shift_left_2 $end
$var wire 32 )" shift_in [31:0] $end
$var wire 32 *" shifted_out [31:0] $end
$upscope $end
$enddefinitions $end
#0
$dumpvars
bz00 *"
bz )"
bx ("
bx '"
z&"
bz %"
z$"
bz #"
bz ""
bz !"
bz ~
z}
bz |
bz {
bz z
zy
bz x
bz w
bx v
bz u
zt
zs
bx r
zq
bz p
zo
bz n
zm
zl
zk
zj
zi
zh
bz g
zf
ze
zd
zc
bz b
za
z`
bz _
z^
bz ]
bz \
bz [
bx Z
bz Y
bz X
bx W
bz V
b0 U
b1 T
b1 S
b0 R
b0 Q
1P
b0 O
0N
b0 M
0L
b1 K
xJ
1I
0H
xG
xF
xE
0D
1C
xB
xA
bx @
bz ?
bz >
bx =
bz <
bz ;
bx :
bz 9
b0x 8
bx 7
bx 6
bx 5
bz 4
z3
bz 2
bz 1
bz 0
bx /
bz .
z-
bx ,
x+
bx *
b0x )
x(
bz '
bz &
bz %
bz $
bx #
bx "
bz !
$end
#10
b11 K
b11 S
xC
xI
xD
xH
b110 T
b1 U
1N
0P
#20
0N
#30
b0 K
b0 S
b10 M
b10 R
1L
b111 T
b110 U
1N
#40
0N
#50
bx K
bx S
bx M
bx R
xL
1A
1B
0E
b0 T
b111 U
1N
#60
0N
#70
b1 K
b1 S
b0 M
b0 R
1C
1I
0L
0D
0H
xA
xB
xE
b1 T
b0 U
1N
#80
0N
#90
b11 K
b11 S
xC
xI
xD
xH
b110 T
b1 U
1N
#100
0N
#110
b0 K
b0 S
b10 M
b10 R
1L
b111 T
b110 U
1N
#120
0N
#130
bx K
bx S
bx M
bx R
xL
1A
1B
0E
b0 T
b111 U
1N
